<?xml version="1.0" encoding="UTF-8"?>

<!-- generated on 2022-10-11 16:45:16 by Eclipse SUMO netconvert Version 1.14.1
<configuration xmlns:xsi="http://www.w3.org/2001/XMLSchema-instance" xsi:noNamespaceSchemaLocation="http://sumo.dlr.de/xsd/netconvertConfiguration.xsd">

    <input>
        <node-files value="../data/salt-lake-city/nodes.nod.xml"/>
        <edge-files value="../data/salt-lake-city/edges.edg.xml"/>
        <connection-files value="../data/salt-lake-city/connections.con.xml"/>
    </input>

    <output>
        <output-file value="../data/salt-lake-city/sumo/net/190.net.xml"/>
    </output>

    <tls_building>
        <tls.minor-left.max-speed value="1"/>
    </tls_building>

    <report>
        <verbose value="true"/>
    </report>

</configuration>
-->

<net version="1.9" junctionCornerDetail="5" limitTurnSpeed="5.50" xmlns:xsi="http://www.w3.org/2001/XMLSchema-instance" xsi:noNamespaceSchemaLocation="http://sumo.dlr.de/xsd/net_file.xsd">

    <location netOffset="425.33,219.37" convBoundary="0.00,0.00,598.00,432.03" origBoundary="-425.33,-219.37,172.67,212.67" projParameter="!"/>

    <edge id=":A_0" function="internal">
        <lane id=":A_0_0" index="0" speed="6.51" length="9.03" shape="423.73,311.63,0.67 423.38,309.18,0.67 422.33,307.43,0.67 420.58,306.38,0.67 418.13,306.03,0.67"/>
    </edge>
    <edge id=":A_1" function="internal">
        <lane id=":A_1_0" index="0" speed="35.00" length="14.40" shape="423.73,311.63,0.67 423.73,297.23,0.62"/>
    </edge>
    <edge id=":A_2" function="internal">
        <lane id=":A_2_0" index="0" speed="6.51" length="9.03" shape="432.53,306.03,0.67 430.08,306.38,0.67 428.33,307.43,0.67 427.28,309.18,0.67 426.93,311.63,0.67"/>
    </edge>
    <edge id=":A_3" function="internal">
        <lane id=":A_3_0" index="0" speed="35.00" length="14.40" shape="432.53,306.03,0.67 418.13,306.03,0.67"/>
    </edge>
    <edge id=":A_4" function="internal">
        <lane id=":A_4_0" index="0" speed="6.51" length="9.03" shape="426.93,297.23,0.62 427.28,299.68,0.63 428.33,301.43,0.65 430.08,302.48,0.66 432.53,302.83,0.67"/>
    </edge>
    <edge id=":A_5" function="internal">
        <lane id=":A_5_0" index="0" speed="35.00" length="14.40" shape="426.93,297.23,0.62 426.93,311.63,0.67"/>
    </edge>
    <edge id=":A_6" function="internal">
        <lane id=":A_6_0" index="0" speed="6.51" length="9.03" shape="418.13,302.83,0.67 420.58,302.48,0.66 422.33,301.43,0.65 423.38,299.68,0.63 423.73,297.23,0.62"/>
    </edge>
    <edge id=":A_7" function="internal">
        <lane id=":A_7_0" index="0" speed="35.00" length="14.40" shape="418.13,302.83,0.67 432.53,302.83,0.67"/>
    </edge>
    <edge id=":AA_0" function="internal">
        <lane id=":AA_0_0" index="0" speed="3.65" length="4.67" shape="340.27,306.03,0.67 339.07,305.23,0.67 338.67,304.43,0.67 339.07,303.63,0.67 340.27,302.83,0.67"/>
    </edge>
    <edge id=":AB_0" function="internal">
        <lane id=":AB_0_0" index="0" speed="3.65" length="4.67" shape="426.93,389.49,0.67 426.13,390.69,0.67 425.33,391.09,0.67 424.53,390.69,0.67 423.73,389.49,0.67"/>
    </edge>
    <edge id=":AC_0" function="internal">
        <lane id=":AC_0_0" index="0" speed="3.65" length="4.67" shape="510.40,302.83,0.67 511.60,303.63,0.67 512.00,304.43,0.67 511.60,305.23,0.67 510.40,306.03,0.67"/>
    </edge>
    <edge id=":B_0" function="internal">
        <lane id=":B_0_0" index="0" speed="6.51" length="9.03" shape="500.47,236.17,-3.16 500.12,233.72,-3.16 499.07,231.97,-3.16 497.32,230.92,-3.16 494.87,230.57,-3.16"/>
    </edge>
    <edge id=":B_1" function="internal">
        <lane id=":B_1_0" index="0" speed="30.00" length="33.60" shape="500.47,236.17,-3.16 500.47,202.57,-3.16"/>
        <lane id=":B_1_1" index="1" speed="30.00" length="33.60" shape="503.67,236.17,-3.16 503.67,202.57,-3.16"/>
        <lane id=":B_1_2" index="2" speed="30.00" length="33.60" shape="506.87,236.17,-3.16 506.87,202.57,-3.16"/>
        <lane id=":B_1_3" index="3" speed="30.00" length="33.60" shape="510.07,236.17,-3.16 510.07,202.57,-3.16"/>
    </edge>
    <edge id=":B_5" function="internal">
        <lane id=":B_5_0" index="0" speed="11.36" length="5.01" shape="510.07,236.17,-3.16 510.78,231.20,-3.16"/>
    </edge>
    <edge id=":B_24" function="internal">
        <lane id=":B_24_0" index="0" speed="11.36" length="24.66" shape="510.78,231.20,-3.16 511.22,228.12,-3.16 514.67,222.37,-3.16 520.42,218.92,-3.16 528.47,217.77,-3.16"/>
    </edge>
    <edge id=":B_6" function="internal">
        <lane id=":B_6_0" index="0" speed="6.51" length="9.03" shape="528.47,230.57,-3.16 526.02,230.92,-3.16 524.27,231.97,-3.16 523.22,233.72,-3.16 522.87,236.17,-3.16"/>
    </edge>
    <edge id=":B_7" function="internal">
        <lane id=":B_7_0" index="0" speed="30.00" length="33.60" shape="528.47,230.57,-3.16 494.87,230.57,-3.16"/>
        <lane id=":B_7_1" index="1" speed="30.00" length="33.60" shape="528.47,227.37,-3.16 494.87,227.37,-3.16"/>
        <lane id=":B_7_2" index="2" speed="30.00" length="33.60" shape="528.47,224.17,-3.16 494.87,224.17,-3.16"/>
        <lane id=":B_7_3" index="3" speed="30.00" length="33.60" shape="528.47,220.97,-3.16 494.87,220.97,-3.16"/>
    </edge>
    <edge id=":B_11" function="internal">
        <lane id=":B_11_0" index="0" speed="11.36" length="5.01" shape="528.47,220.97,-3.16 523.51,220.26,-3.16"/>
    </edge>
    <edge id=":B_25" function="internal">
        <lane id=":B_25_0" index="0" speed="11.36" length="24.66" shape="523.51,220.26,-3.16 520.42,219.82,-3.16 514.67,216.37,-3.16 511.22,210.62,-3.16 510.07,202.57,-3.16"/>
    </edge>
    <edge id=":B_12" function="internal">
        <lane id=":B_12_0" index="0" speed="6.51" length="9.03" shape="522.87,202.57,-3.16 523.22,205.02,-3.16 524.27,206.77,-3.16 526.02,207.82,-3.16 528.47,208.17,-3.16"/>
    </edge>
    <edge id=":B_13" function="internal">
        <lane id=":B_13_0" index="0" speed="30.00" length="33.60" shape="522.87,202.57,-3.16 522.87,236.17,-3.16"/>
        <lane id=":B_13_1" index="1" speed="30.00" length="33.60" shape="519.67,202.57,-3.16 519.67,236.17,-3.16"/>
        <lane id=":B_13_2" index="2" speed="30.00" length="33.60" shape="516.47,202.57,-3.16 516.47,236.17,-3.16"/>
        <lane id=":B_13_3" index="3" speed="30.00" length="33.60" shape="513.27,202.57,-3.16 513.27,236.17,-3.16"/>
    </edge>
    <edge id=":B_17" function="internal">
        <lane id=":B_17_0" index="0" speed="11.36" length="5.01" shape="513.27,202.57,-3.16 512.56,207.53,-3.16"/>
    </edge>
    <edge id=":B_26" function="internal">
        <lane id=":B_26_0" index="0" speed="11.36" length="24.66" shape="512.56,207.53,-3.16 512.12,210.62,-3.16 508.67,216.37,-3.16 502.92,219.82,-3.16 494.87,220.97,-3.16"/>
    </edge>
    <edge id=":B_18" function="internal">
        <lane id=":B_18_0" index="0" speed="6.51" length="9.03" shape="494.87,208.17,-3.16 497.32,207.82,-3.16 499.07,206.77,-3.16 500.12,205.02,-3.16 500.47,202.57,-3.16"/>
    </edge>
    <edge id=":B_19" function="internal">
        <lane id=":B_19_0" index="0" speed="30.00" length="33.60" shape="494.87,208.17,-3.16 528.47,208.17,-3.16"/>
        <lane id=":B_19_1" index="1" speed="30.00" length="33.60" shape="494.87,211.37,-3.16 528.47,211.37,-3.16"/>
        <lane id=":B_19_2" index="2" speed="30.00" length="33.60" shape="494.87,214.57,-3.16 528.47,214.57,-3.16"/>
        <lane id=":B_19_3" index="3" speed="30.00" length="33.60" shape="494.87,217.77,-3.16 528.47,217.77,-3.16"/>
    </edge>
    <edge id=":B_23" function="internal">
        <lane id=":B_23_0" index="0" speed="11.36" length="5.01" shape="494.87,217.77,-3.16 499.83,218.48,-3.16"/>
    </edge>
    <edge id=":B_27" function="internal">
        <lane id=":B_27_0" index="0" speed="11.36" length="24.66" shape="499.83,218.48,-3.16 502.92,218.92,-3.16 508.67,222.37,-3.16 512.12,228.12,-3.16 513.27,236.17,-3.16"/>
    </edge>
    <edge id=":BA_0" function="internal">
        <lane id=":BA_0_0" index="0" speed="3.65" length="4.67" shape="513.27,305.70,-3.16 512.47,306.90,-3.16 511.67,307.30,-3.16 510.87,306.90,-3.16 510.07,305.70,-3.16"/>
    </edge>
    <edge id=":BB_0" function="internal">
        <lane id=":BB_0_0" index="0" speed="3.65" length="4.67" shape="598.00,217.77,-3.16 599.20,218.57,-3.16 599.60,219.37,-3.16 599.20,220.17,-3.16 598.00,220.97,-3.16"/>
    </edge>
    <edge id=":BC_0" function="internal">
        <lane id=":BC_0_0" index="0" speed="3.65" length="4.67" shape="510.07,133.03,-3.16 510.87,131.83,-3.16 511.67,131.43,-3.16 512.47,131.83,-3.16 513.27,133.03,-3.16"/>
    </edge>
    <edge id=":C_0" function="internal">
        <lane id=":C_0_0" index="0" speed="6.51" length="9.03" shape="423.73,116.88,1.06 423.38,114.43,1.08 422.33,112.68,1.10 420.58,111.63,1.12 418.13,111.28,1.14"/>
    </edge>
    <edge id=":C_1" function="internal">
        <lane id=":C_1_0" index="0" speed="30.00" length="14.40" shape="423.73,116.88,1.06 423.73,102.48,1.14"/>
    </edge>
    <edge id=":C_2" function="internal">
        <lane id=":C_2_0" index="0" speed="6.51" length="9.03" shape="432.53,111.28,1.14 430.08,111.63,1.12 428.33,112.68,1.10 427.28,114.43,1.08 426.93,116.88,1.06"/>
    </edge>
    <edge id=":C_3" function="internal">
        <lane id=":C_3_0" index="0" speed="30.00" length="14.40" shape="432.53,111.28,1.14 418.13,111.28,1.14"/>
    </edge>
    <edge id=":C_4" function="internal">
        <lane id=":C_4_0" index="0" speed="6.51" length="9.03" shape="426.93,102.48,1.14 427.28,104.93,1.14 428.33,106.68,1.14 430.08,107.73,1.14 432.53,108.08,1.14"/>
    </edge>
    <edge id=":C_5" function="internal">
        <lane id=":C_5_0" index="0" speed="30.00" length="14.40" shape="426.93,102.48,1.14 426.93,116.88,1.06"/>
    </edge>
    <edge id=":C_6" function="internal">
        <lane id=":C_6_0" index="0" speed="6.51" length="9.03" shape="418.13,108.08,1.14 420.58,107.73,1.14 422.33,106.68,1.14 423.38,104.93,1.14 423.73,102.48,1.14"/>
    </edge>
    <edge id=":C_7" function="internal">
        <lane id=":C_7_0" index="0" speed="30.00" length="14.40" shape="418.13,108.08,1.14 432.53,108.08,1.14"/>
    </edge>
    <edge id=":CA_0" function="internal">
        <lane id=":CA_0_0" index="0" speed="3.65" length="4.67" shape="535.02,108.08,1.14 536.22,108.88,1.14 536.62,109.68,1.14 536.22,110.48,1.14 535.02,111.28,1.14"/>
    </edge>
    <edge id=":CB_0" function="internal">
        <lane id=":CB_0_0" index="0" speed="3.65" length="4.67" shape="423.73,0.00,1.14 424.53,-1.20,1.14 425.33,-1.60,1.14 426.13,-1.20,1.14 426.93,0.00,1.14"/>
    </edge>
    <edge id=":CC_0" function="internal">
        <lane id=":CC_0_0" index="0" speed="3.65" length="4.67" shape="315.65,111.28,1.14 314.45,110.48,1.14 314.05,109.68,1.14 314.45,108.88,1.14 315.65,108.08,1.14"/>
    </edge>
    <edge id=":C_intern_0" function="internal">
        <lane id=":C_intern_0_0" index="0" speed="30.00" length="8.40" shape="426.93,165.37,0.56 427.43,167.83,0.54 428.53,169.37,0.52 429.63,170.91,0.50 430.13,173.37,0.48"/>
        <lane id=":C_intern_0_1" index="1" speed="30.00" length="8.40" shape="426.93,165.37,0.56 426.93,173.37,0.48"/>
    </edge>
    <edge id=":D_0" function="internal">
        <lane id=":D_0_0" index="0" speed="8.10" length="14.57" shape="207.87,236.17,2.79 207.12,233.72,2.79 204.87,231.97,2.79 201.12,230.92,2.79 195.87,230.57,2.79"/>
    </edge>
    <edge id=":D_1" function="internal">
        <lane id=":D_1_0" index="0" speed="30.00" length="34.33" shape="207.87,236.17,2.79 206.87,229.10,2.79 204.67,222.03,2.79 202.47,213.63,2.79 201.47,202.57,2.79"/>
        <lane id=":D_1_1" index="1" speed="30.00" length="34.33" shape="211.07,236.17,2.79 210.07,229.10,2.79 207.87,222.03,2.79 205.67,213.63,2.79 204.67,202.57,2.79"/>
    </edge>
    <edge id=":D_3" function="internal">
        <lane id=":D_3_0" index="0" speed="11.36" length="15.40" shape="211.07,236.17,2.79 212.22,228.12,2.79 215.67,222.37,2.79 216.15,222.08,2.79"/>
    </edge>
    <edge id=":D_16" function="internal">
        <lane id=":D_16_0" index="0" speed="11.36" length="14.27" shape="216.15,222.08,2.79 221.42,218.92,2.79 229.47,217.77,2.79"/>
    </edge>
    <edge id=":D_4" function="internal">
        <lane id=":D_4_0" index="0" speed="8.10" length="14.57" shape="229.47,224.17,2.79 227.02,224.92,2.79 225.27,227.17,2.79 224.22,230.92,2.79 223.87,236.17,2.79"/>
    </edge>
    <edge id=":D_5" function="internal">
        <lane id=":D_5_0" index="0" speed="30.00" length="34.33" shape="229.47,224.17,2.79 222.40,225.17,2.79 215.33,227.37,2.79 206.93,229.57,2.79 195.87,230.57,2.79"/>
        <lane id=":D_5_1" index="1" speed="30.00" length="34.33" shape="229.47,220.97,2.79 222.40,221.97,2.79 215.33,224.17,2.79 206.93,226.37,2.79 195.87,227.37,2.79"/>
    </edge>
    <edge id=":D_7" function="internal">
        <lane id=":D_7_0" index="0" speed="11.36" length="15.40" shape="229.47,220.97,2.79 221.42,219.82,2.79 215.67,216.37,2.79 215.38,215.88,2.79"/>
    </edge>
    <edge id=":D_17" function="internal">
        <lane id=":D_17_0" index="0" speed="11.36" length="14.27" shape="215.38,215.88,2.79 212.22,210.62,2.79 211.07,202.57,2.79"/>
    </edge>
    <edge id=":D_8" function="internal">
        <lane id=":D_8_0" index="0" speed="8.10" length="14.57" shape="217.47,202.57,2.79 218.22,205.02,2.79 220.47,206.77,2.79 224.22,207.82,2.79 229.47,208.17,2.79"/>
    </edge>
    <edge id=":D_9" function="internal">
        <lane id=":D_9_0" index="0" speed="30.00" length="34.33" shape="217.47,202.57,2.79 218.47,209.63,2.79 220.67,216.70,2.79 222.87,225.11,2.79 223.87,236.17,2.79"/>
        <lane id=":D_9_1" index="1" speed="30.00" length="34.33" shape="214.27,202.57,2.79 215.27,209.63,2.79 217.47,216.70,2.79 219.67,225.11,2.79 220.67,236.17,2.79"/>
    </edge>
    <edge id=":D_11" function="internal">
        <lane id=":D_11_0" index="0" speed="11.36" length="15.40" shape="214.27,202.57,2.79 213.12,210.62,2.79 209.67,216.37,2.79 209.18,216.66,2.79"/>
    </edge>
    <edge id=":D_18" function="internal">
        <lane id=":D_18_0" index="0" speed="11.36" length="14.27" shape="209.18,216.66,2.79 203.92,219.82,2.79 195.87,220.97,2.79"/>
    </edge>
    <edge id=":D_12" function="internal">
        <lane id=":D_12_0" index="0" speed="8.10" length="14.57" shape="195.87,214.57,2.79 198.32,213.82,2.79 200.07,211.57,2.79 201.12,207.82,2.79 201.47,202.57,2.79"/>
    </edge>
    <edge id=":D_13" function="internal">
        <lane id=":D_13_0" index="0" speed="30.00" length="34.33" shape="195.87,214.57,2.79 202.93,213.57,2.79 210.00,211.37,2.79 218.41,209.17,2.79 229.47,208.17,2.79"/>
        <lane id=":D_13_1" index="1" speed="30.00" length="34.33" shape="195.87,217.77,2.79 202.93,216.77,2.79 210.00,214.57,2.79 218.41,212.37,2.79 229.47,211.37,2.79"/>
    </edge>
    <edge id=":D_15" function="internal">
        <lane id=":D_15_0" index="0" speed="11.36" length="15.40" shape="195.87,217.77,2.79 203.92,218.92,2.79 209.67,222.37,2.79 209.96,222.85,2.79"/>
    </edge>
    <edge id=":D_19" function="internal">
        <lane id=":D_19_0" index="0" speed="11.36" length="14.27" shape="209.96,222.85,2.79 213.12,228.12,2.79 214.27,236.17,2.79"/>
    </edge>
    <edge id=":DA_0" function="internal">
        <lane id=":DA_0_0" index="0" speed="3.65" length="4.67" shape="211.07,6.70,2.79 211.87,5.50,2.79 212.67,5.10,2.79 213.47,5.50,2.79 214.27,6.70,2.79"/>
    </edge>
    <edge id=":DB_0" function="internal">
        <lane id=":DB_0_0" index="0" speed="3.65" length="4.67" shape="-0.00,220.97,2.79 -1.20,220.17,2.79 -1.60,219.37,2.79 -1.20,218.57,2.79 -0.00,217.77,2.79"/>
    </edge>
    <edge id=":DC_0" function="internal">
        <lane id=":DC_0_0" index="0" speed="3.65" length="4.67" shape="214.27,432.03,2.79 213.47,433.23,2.79 212.67,433.63,2.79 211.87,433.23,2.79 211.07,432.03,2.79"/>
    </edge>
    <edge id=":TL_0" function="internal">
        <lane id=":TL_0_0" index="0" speed="32.50" length="33.60" shape="423.73,236.17,0.13 423.73,202.57,0.17"/>
    </edge>
    <edge id=":TL_1" function="internal">
        <lane id=":TL_1_0" index="0" speed="7.33" length="11.73" shape="435.73,230.57 431.88,230.92,0.04 429.13,231.97,0.08 427.48,233.72,0.10 426.93,236.17,0.13"/>
    </edge>
    <edge id=":TL_2" function="internal">
        <lane id=":TL_2_0" index="0" speed="30.00" length="18.43" shape="435.73,230.57 430.35,229.57,0.03 426.93,227.37,0.05 423.52,225.17,0.07 418.13,224.17,0.09"/>
        <lane id=":TL_2_1" index="1" speed="30.00" length="18.43" shape="435.73,227.37 430.35,226.37,0.03 426.93,224.17,0.05 423.52,221.97,0.07 418.13,220.97,0.09"/>
        <lane id=":TL_2_2" index="2" speed="30.00" length="18.43" shape="435.73,224.17 430.47,223.67,0.03 426.93,222.57,0.05 423.40,221.47,0.07 418.13,220.97,0.09"/>
        <lane id=":TL_2_3" index="3" speed="30.00" length="18.43" shape="435.73,220.97 418.13,220.97,0.09"/>
    </edge>
    <edge id=":TL_6" function="internal">
        <lane id=":TL_6_0" index="0" speed="10.41" length="3.37" shape="435.73,220.97 432.44,220.25,0.02"/>
    </edge>
    <edge id=":TL_16" function="internal">
        <lane id=":TL_16_0" index="0" speed="10.41" length="21.36" shape="432.44,220.25,0.02 430.48,219.82,0.04 426.73,216.37,0.07 424.48,210.62,0.12 423.73,202.57,0.17"/>
    </edge>
    <edge id=":TL_7" function="internal">
        <lane id=":TL_7_0" index="0" speed="6.51" length="9.03" shape="430.13,202.57,0.17 430.48,205.02,0.13 431.53,206.77,0.09 433.28,207.82,0.05 435.73,208.17"/>
    </edge>
    <edge id=":TL_8" function="internal">
        <lane id=":TL_8_0" index="0" speed="32.50" length="33.76" shape="430.13,202.57,0.17 429.63,211.33,0.16 428.53,221.24,0.15 427.43,230.21,0.14 426.93,236.17,0.13"/>
    </edge>
    <edge id=":TL_9" function="internal">
        <lane id=":TL_9_0" index="0" speed="9.94" length="8.55" shape="426.93,202.57,0.17 426.38,210.62,0.15 426.25,211.08,0.14"/>
    </edge>
    <edge id=":TL_17" function="internal">
        <lane id=":TL_17_0" index="0" speed="9.94" length="13.93" shape="426.25,211.08,0.14 424.73,216.37,0.12 421.98,219.82,0.11 418.13,220.97,0.09"/>
    </edge>
    <edge id=":TL_10" function="internal">
        <lane id=":TL_10_0" index="0" speed="6.51" length="9.03" shape="418.13,208.17,0.10 420.58,207.82,0.12 422.33,206.77,0.14 423.38,205.02,0.15 423.73,202.57,0.17"/>
    </edge>
    <edge id=":TL_11" function="internal">
        <lane id=":TL_11_0" index="0" speed="30.00" length="17.60" shape="418.13,208.17,0.10 435.73,208.17"/>
        <lane id=":TL_11_1" index="1" speed="30.00" length="17.60" shape="418.13,211.37,0.10 435.73,211.37"/>
        <lane id=":TL_11_2" index="2" speed="30.00" length="17.60" shape="418.13,214.57,0.10 435.73,214.57"/>
        <lane id=":TL_11_3" index="3" speed="30.00" length="17.60" shape="418.13,217.77,0.10 435.73,217.77"/>
    </edge>
    <edge id=":TL_15" function="internal">
        <lane id=":TL_15_0" index="0" speed="9.94" length="2.58" shape="418.13,217.77,0.10 420.60,218.50,0.11"/>
    </edge>
    <edge id=":TL_18" function="internal">
        <lane id=":TL_18_0" index="0" speed="9.94" length="19.90" shape="420.60,218.50,0.11 421.98,218.92,0.11 424.73,222.37,0.11 426.38,228.12,0.12 426.93,236.17,0.13"/>
    </edge>

    <edge id="A2AA" from="A" to="AA" priority="-1">
        <lane id="A2AA_0" index="0" speed="35.00" length="77.86" shape="418.13,306.03,0.67 340.27,306.03,0.67"/>
    </edge>
    <edge id="A2AB" from="A" to="AB" priority="-1">
        <lane id="A2AB_0" index="0" speed="35.00" length="77.86" shape="426.93,311.63,0.67 426.93,389.49,0.67"/>
    </edge>
    <edge id="A2AC" from="A" to="AC" priority="-1">
        <lane id="A2AC_0" index="0" speed="35.00" length="77.86" shape="432.53,302.83,0.67 510.40,302.83,0.67"/>
    </edge>
    <edge id="A2TL" from="A" to="TL" priority="-1">
        <lane id="A2TL_0" index="0" speed="35.00" length="61.06" shape="423.73,297.23,0.62 423.73,236.17,0.13"/>
    </edge>
    <edge id="AA2A" from="AA" to="A" priority="-1">
        <lane id="AA2A_0" index="0" speed="35.00" length="77.86" shape="340.27,302.83,0.67 418.13,302.83,0.67"/>
    </edge>
    <edge id="AB2A" from="AB" to="A" priority="-1">
        <lane id="AB2A_0" index="0" speed="35.00" length="77.86" shape="423.73,389.49,0.67 423.73,311.63,0.67"/>
    </edge>
    <edge id="AC2A" from="AC" to="A" priority="-1">
        <lane id="AC2A_0" index="0" speed="35.00" length="77.86" shape="510.40,306.03,0.67 432.53,306.03,0.67"/>
    </edge>
    <edge id="B2BA" from="B" to="BA" priority="-1">
        <lane id="B2BA_0" index="0" speed="30.00" length="69.53" shape="522.87,236.17,-3.16 522.87,305.70,-3.16"/>
        <lane id="B2BA_1" index="1" speed="30.00" length="69.53" shape="519.67,236.17,-3.16 519.67,305.70,-3.16"/>
        <lane id="B2BA_2" index="2" speed="30.00" length="69.53" shape="516.47,236.17,-3.16 516.47,305.70,-3.16"/>
        <lane id="B2BA_3" index="3" speed="30.00" length="69.53" shape="513.27,236.17,-3.16 513.27,305.70,-3.16"/>
    </edge>
    <edge id="B2BB" from="B" to="BB" priority="-1">
        <lane id="B2BB_0" index="0" speed="30.00" length="69.53" shape="528.47,208.17,-3.16 598.00,208.17,-3.16"/>
        <lane id="B2BB_1" index="1" speed="30.00" length="69.53" shape="528.47,211.37,-3.16 598.00,211.37,-3.16"/>
        <lane id="B2BB_2" index="2" speed="30.00" length="69.53" shape="528.47,214.57,-3.16 598.00,214.57,-3.16"/>
        <lane id="B2BB_3" index="3" speed="30.00" length="69.53" shape="528.47,217.77,-3.16 598.00,217.77,-3.16"/>
    </edge>
    <edge id="B2BC" from="B" to="BC" priority="-1">
        <lane id="B2BC_0" index="0" speed="30.00" length="69.53" shape="500.47,202.57,-3.16 500.47,133.03,-3.16"/>
        <lane id="B2BC_1" index="1" speed="30.00" length="69.53" shape="503.67,202.57,-3.16 503.67,133.03,-3.16"/>
        <lane id="B2BC_2" index="2" speed="30.00" length="69.53" shape="506.87,202.57,-3.16 506.87,133.03,-3.16"/>
        <lane id="B2BC_3" index="3" speed="30.00" length="69.53" shape="510.07,202.57,-3.16 510.07,133.03,-3.16"/>
    </edge>
    <edge id="B2TL" from="B" to="TL" priority="-1">
        <lane id="B2TL_0" index="0" speed="30.00" length="59.22" shape="494.87,230.57,-3.16 435.73,230.57"/>
        <lane id="B2TL_1" index="1" speed="30.00" length="59.22" shape="494.87,227.37,-3.16 435.73,227.37"/>
        <lane id="B2TL_2" index="2" speed="30.00" length="59.22" shape="494.87,224.17,-3.16 435.73,224.17"/>
        <lane id="B2TL_3" index="3" speed="30.00" length="59.22" shape="494.87,220.97,-3.16 435.73,220.97"/>
    </edge>
    <edge id="BA2B" from="BA" to="B" priority="-1">
        <lane id="BA2B_0" index="0" speed="30.00" length="69.53" shape="500.47,305.70,-3.16 500.47,236.17,-3.16"/>
        <lane id="BA2B_1" index="1" speed="30.00" length="69.53" shape="503.67,305.70,-3.16 503.67,236.17,-3.16"/>
        <lane id="BA2B_2" index="2" speed="30.00" length="69.53" shape="506.87,305.70,-3.16 506.87,236.17,-3.16"/>
        <lane id="BA2B_3" index="3" speed="30.00" length="69.53" shape="510.07,305.70,-3.16 510.07,236.17,-3.16"/>
    </edge>
    <edge id="BB2B" from="BB" to="B" priority="-1">
        <lane id="BB2B_0" index="0" speed="30.00" length="69.53" shape="598.00,230.57,-3.16 528.47,230.57,-3.16"/>
        <lane id="BB2B_1" index="1" speed="30.00" length="69.53" shape="598.00,227.37,-3.16 528.47,227.37,-3.16"/>
        <lane id="BB2B_2" index="2" speed="30.00" length="69.53" shape="598.00,224.17,-3.16 528.47,224.17,-3.16"/>
        <lane id="BB2B_3" index="3" speed="30.00" length="69.53" shape="598.00,220.97,-3.16 528.47,220.97,-3.16"/>
    </edge>
    <edge id="BC2B" from="BC" to="B" priority="-1">
        <lane id="BC2B_0" index="0" speed="30.00" length="69.53" shape="522.87,133.03,-3.16 522.87,202.57,-3.16"/>
        <lane id="BC2B_1" index="1" speed="30.00" length="69.53" shape="519.67,133.03,-3.16 519.67,202.57,-3.16"/>
        <lane id="BC2B_2" index="2" speed="30.00" length="69.53" shape="516.47,133.03,-3.16 516.47,202.57,-3.16"/>
        <lane id="BC2B_3" index="3" speed="30.00" length="69.53" shape="513.27,133.03,-3.16 513.27,202.57,-3.16"/>
    </edge>
    <edge id="C2CA" from="C" to="CA" priority="-1">
        <lane id="C2CA_0" index="0" speed="30.00" length="102.48" shape="432.53,108.08,1.14 535.02,108.08,1.14"/>
    </edge>
    <edge id="C2CB" from="C" to="CB" priority="-1">
        <lane id="C2CB_0" index="0" speed="30.00" length="102.48" shape="423.73,102.48,1.14 423.73,0.00,1.14"/>
    </edge>
    <edge id="C2CC" from="C" to="CC" priority="-1">
        <lane id="C2CC_0" index="0" speed="30.00" length="102.48" shape="418.13,111.28,1.14 315.65,111.28,1.14"/>
    </edge>
    <edge id="C2TL" from="C" to="C_intern" priority="-1">
        <lane id="C2TL_0" index="0" speed="30.00" length="48.49" shape="426.93,116.88,1.06 426.93,165.37,0.56"/>
    </edge>
    <edge id="C2TL_intern" from="C_intern" to="TL" priority="-1">
        <lane id="C2TL_intern_0" index="0" speed="30.00" length="29.20" shape="430.13,173.37,0.48 430.13,202.57,0.17"/>
        <lane id="C2TL_intern_1" index="1" speed="30.00" length="29.20" shape="426.93,173.37,0.48 426.93,202.57,0.17"/>
    </edge>
    <edge id="CA2C" from="CA" to="C" priority="-1">
        <lane id="CA2C_0" index="0" speed="30.00" length="102.48" shape="535.02,111.28,1.14 432.53,111.28,1.14"/>
    </edge>
    <edge id="CB2C" from="CB" to="C" priority="-1">
        <lane id="CB2C_0" index="0" speed="30.00" length="102.48" shape="426.93,0.00,1.14 426.93,102.48,1.14"/>
    </edge>
    <edge id="CC2C" from="CC" to="C" priority="-1">
        <lane id="CC2C_0" index="0" speed="30.00" length="102.48" shape="315.65,108.08,1.14 418.13,108.08,1.14"/>
    </edge>
    <edge id="D2DA" from="D" to="DA" priority="-1">
        <lane id="D2DA_0" index="0" speed="30.00" length="195.87" shape="201.47,202.57,2.79 201.47,6.70,2.79"/>
        <lane id="D2DA_1" index="1" speed="30.00" length="195.87" shape="204.67,202.57,2.79 204.67,6.70,2.79"/>
        <lane id="D2DA_2" index="2" speed="30.00" length="195.87" shape="207.87,202.57,2.79 207.87,6.70,2.79"/>
        <lane id="D2DA_3" index="3" speed="30.00" length="195.87" shape="211.07,202.57,2.79 211.07,6.70,2.79"/>
    </edge>
    <edge id="D2DB" from="D" to="DB" priority="-1">
        <lane id="D2DB_0" index="0" speed="30.00" length="195.87" shape="195.87,230.57,2.79 -0.00,230.57,2.79"/>
        <lane id="D2DB_1" index="1" speed="30.00" length="195.87" shape="195.87,227.37,2.79 -0.00,227.37,2.79"/>
        <lane id="D2DB_2" index="2" speed="30.00" length="195.87" shape="195.87,224.17,2.79 -0.00,224.17,2.79"/>
        <lane id="D2DB_3" index="3" speed="30.00" length="195.87" shape="195.87,220.97,2.79 -0.00,220.97,2.79"/>
    </edge>
    <edge id="D2DC" from="D" to="DC" priority="-1">
        <lane id="D2DC_0" index="0" speed="30.00" length="195.87" shape="223.87,236.17,2.79 223.87,432.03,2.79"/>
        <lane id="D2DC_1" index="1" speed="30.00" length="195.87" shape="220.67,236.17,2.79 220.67,432.03,2.79"/>
        <lane id="D2DC_2" index="2" speed="30.00" length="195.87" shape="217.47,236.17,2.79 217.47,432.03,2.79"/>
        <lane id="D2DC_3" index="3" speed="30.00" length="195.87" shape="214.27,236.17,2.79 214.27,432.03,2.79"/>
    </edge>
    <edge id="D2TL" from="D" to="TL" priority="-1">
        <lane id="D2TL_0" index="0" speed="30.00" length="188.69" shape="229.47,208.17,2.79 418.13,208.17,0.10"/>
        <lane id="D2TL_1" index="1" speed="30.00" length="188.69" shape="229.47,211.37,2.79 418.13,211.37,0.10"/>
        <lane id="D2TL_2" index="2" speed="30.00" length="188.69" shape="229.47,214.57,2.79 418.13,214.57,0.10"/>
        <lane id="D2TL_3" index="3" speed="30.00" length="188.69" shape="229.47,217.77,2.79 418.13,217.77,0.10"/>
    </edge>
    <edge id="DA2D" from="DA" to="D" priority="-1">
        <lane id="DA2D_0" index="0" speed="30.00" length="195.87" shape="217.47,6.70,2.79 217.47,202.57,2.79"/>
        <lane id="DA2D_1" index="1" speed="30.00" length="195.87" shape="214.27,6.70,2.79 214.27,202.57,2.79"/>
    </edge>
    <edge id="DB2D" from="DB" to="D" priority="-1">
        <lane id="DB2D_0" index="0" speed="30.00" length="195.87" shape="-0.00,214.57,2.79 195.87,214.57,2.79"/>
        <lane id="DB2D_1" index="1" speed="30.00" length="195.87" shape="-0.00,217.77,2.79 195.87,217.77,2.79"/>
    </edge>
    <edge id="DC2D" from="DC" to="D" priority="-1">
        <lane id="DC2D_0" index="0" speed="30.00" length="195.87" shape="207.87,432.03,2.79 207.87,236.17,2.79"/>
        <lane id="DC2D_1" index="1" speed="30.00" length="195.87" shape="211.07,432.03,2.79 211.07,236.17,2.79"/>
    </edge>
    <edge id="TL2A" from="TL" to="A" priority="-1">
        <lane id="TL2A_0" index="0" speed="35.00" length="61.06" shape="426.93,236.17,0.13 426.93,297.23,0.62"/>
    </edge>
    <edge id="TL2B" from="TL" to="B" priority="-1">
        <lane id="TL2B_0" index="0" speed="30.00" length="59.22" shape="435.73,208.17 494.87,208.17,-3.16"/>
        <lane id="TL2B_1" index="1" speed="30.00" length="59.22" shape="435.73,211.37 494.87,211.37,-3.16"/>
        <lane id="TL2B_2" index="2" speed="30.00" length="59.22" shape="435.73,214.57 494.87,214.57,-3.16"/>
        <lane id="TL2B_3" index="3" speed="30.00" length="59.22" shape="435.73,217.77 494.87,217.77,-3.16"/>
    </edge>
    <edge id="TL2C" from="TL" to="C" priority="-1">
        <lane id="TL2C_0" index="0" speed="30.00" length="85.69" shape="423.73,202.57,0.17 423.73,116.88,1.06"/>
    </edge>
    <edge id="TL2D" from="TL" to="D" priority="-1">
        <lane id="TL2D_0" index="0" speed="30.00" length="188.69" shape="418.13,224.17,0.09 229.47,224.17,2.79"/>
        <lane id="TL2D_1" index="1" speed="30.00" length="188.69" shape="418.13,220.97,0.09 229.47,220.97,2.79"/>
    </edge>

    <tlLogic id="A" type="static" programID="0" offset="0">
        <phase duration="38" state="GGrrGGrr"/>
        <phase duration="7"  state="yyrryyrr"/>
        <phase duration="38" state="rrGGrrGG"/>
        <phase duration="7"  state="rryyrryy"/>
    </tlLogic>
    <tlLogic id="AA" type="static" programID="0" offset="0">
        <phase duration="78" state="G"/>
        <phase duration="7"  state="y"/>
        <phase duration="5"  state="r"/>
    </tlLogic>
    <tlLogic id="AB" type="static" programID="0" offset="0">
        <phase duration="78" state="G"/>
        <phase duration="7"  state="y"/>
        <phase duration="5"  state="r"/>
    </tlLogic>
    <tlLogic id="AC" type="static" programID="0" offset="0">
        <phase duration="78" state="G"/>
        <phase duration="7"  state="y"/>
        <phase duration="5"  state="r"/>
    </tlLogic>
    <tlLogic id="B" type="static" programID="0" offset="0">
        <phase duration="39" state="GGGGGgrrrrrrGGGGGgrrrrrr"/>
        <phase duration="6"  state="yyyyyyrrrrrryyyyyyrrrrrr"/>
        <phase duration="39" state="rrrrrrGGGGGgrrrrrrGGGGGg"/>
        <phase duration="6"  state="rrrrrryyyyyyrrrrrryyyyyy"/>
    </tlLogic>
    <tlLogic id="BA" type="static" programID="0" offset="0">
        <phase duration="79" state="G"/>
        <phase duration="6"  state="y"/>
        <phase duration="5"  state="r"/>
    </tlLogic>
    <tlLogic id="BB" type="static" programID="0" offset="0">
        <phase duration="79" state="G"/>
        <phase duration="6"  state="y"/>
        <phase duration="5"  state="r"/>
    </tlLogic>
    <tlLogic id="BC" type="static" programID="0" offset="0">
        <phase duration="79" state="G"/>
        <phase duration="6"  state="y"/>
        <phase duration="5"  state="r"/>
    </tlLogic>
    <tlLogic id="C" type="static" programID="0" offset="0">
        <phase duration="39" state="GGrrGGrr"/>
        <phase duration="6"  state="yyrryyrr"/>
        <phase duration="39" state="rrGGrrGG"/>
        <phase duration="6"  state="rryyrryy"/>
    </tlLogic>
    <tlLogic id="CA" type="static" programID="0" offset="0">
        <phase duration="79" state="G"/>
        <phase duration="6"  state="y"/>
        <phase duration="5"  state="r"/>
    </tlLogic>
    <tlLogic id="CB" type="static" programID="0" offset="0">
        <phase duration="79" state="G"/>
        <phase duration="6"  state="y"/>
        <phase duration="5"  state="r"/>
    </tlLogic>
    <tlLogic id="CC" type="static" programID="0" offset="0">
        <phase duration="79" state="G"/>
        <phase duration="6"  state="y"/>
        <phase duration="5"  state="r"/>
    </tlLogic>
    <tlLogic id="D" type="static" programID="0" offset="0">
        <phase duration="39" state="GGGgrrrrGGGgrrrr"/>
        <phase duration="6"  state="yyyyrrrryyyyrrrr"/>
        <phase duration="39" state="rrrrGGGgrrrrGGGg"/>
        <phase duration="6"  state="rrrryyyyrrrryyyy"/>
    </tlLogic>
    <tlLogic id="DA" type="static" programID="0" offset="0">
        <phase duration="79" state="G"/>
        <phase duration="6"  state="y"/>
        <phase duration="5"  state="r"/>
    </tlLogic>
    <tlLogic id="DB" type="static" programID="0" offset="0">
        <phase duration="79" state="G"/>
        <phase duration="6"  state="y"/>
        <phase duration="5"  state="r"/>
    </tlLogic>
    <tlLogic id="DC" type="static" programID="0" offset="0">
        <phase duration="79" state="G"/>
        <phase duration="6"  state="y"/>
        <phase duration="5"  state="r"/>
    </tlLogic>
    <tlLogic id="TL" type="static" programID="0" offset="0">
        <phase duration="32" state="rGGggGgsrrGGGGGg"/>
        <phase duration="7"  state="ryyyyyysrryyyyyy"/>
        <phase duration="31" state="GsrrrrrGGrsrrrrr"/>
        <phase duration="7"  state="ysrrrrryyrsrrrrr"/>
        <phase duration="6"  state="rsrrrrrGGGsrrrrr"/>
        <phase duration="7"  state="rsrrrrryyysrrrrr"/>
    </tlLogic>

    <junction id="A" type="traffic_light" x="425.33" y="304.43" z="0.67" incLanes="AB2A_0 AC2A_0 TL2A_0 AA2A_0" intLanes=":A_0_0 :A_1_0 :A_2_0 :A_3_0 :A_4_0 :A_5_0 :A_6_0 :A_7_0" shape="422.13,311.63,0.67 428.53,311.63,0.67 428.98,309.41,0.67 429.53,308.63,0.67 430.31,308.07,0.67 431.31,307.74,0.67 432.53,307.63,0.67 432.53,301.23,0.67 430.31,300.78,0.67 429.53,300.23,0.67 428.98,299.45,0.67 428.65,298.45,0.67 428.53,297.23,0.67 422.13,297.23,0.67 421.69,299.45,0.67 421.13,300.23,0.67 420.36,300.78,0.67 419.36,301.12,0.67 418.13,301.23,0.67 418.13,307.63,0.67 420.36,308.07,0.67 421.13,308.63,0.67 421.69,309.41,0.67 422.02,310.41,0.67">
        <request index="0" response="00000000" foes="00001000" cont="0"/>
        <request index="1" response="00000000" foes="11001000" cont="0"/>
        <request index="2" response="00100000" foes="00100000" cont="0"/>
        <request index="3" response="00100011" foes="00100011" cont="0"/>
        <request index="4" response="00000000" foes="10000000" cont="0"/>
        <request index="5" response="00000000" foes="10001100" cont="0"/>
        <request index="6" response="00000010" foes="00000010" cont="0"/>
        <request index="7" response="00110010" foes="00110010" cont="0"/>
    </junction>
    <junction id="AA" type="traffic_light" x="340.27" y="304.43" z="0.67" incLanes="A2AA_0" intLanes=":AA_0_0" shape="340.27,304.43,0.67 340.27,307.63,0.67 340.27,304.43,0.67">
        <request index="0" response="0" foes="0" cont="0"/>
    </junction>
    <junction id="AB" type="traffic_light" x="425.33" y="389.49" z="0.67" incLanes="A2AB_0" intLanes=":AB_0_0" shape="425.33,389.49,0.67 428.53,389.49,0.67 425.33,389.49,0.67">
        <request index="0" response="0" foes="0" cont="0"/>
    </junction>
    <junction id="AC" type="traffic_light" x="510.40" y="304.43" z="0.67" incLanes="A2AC_0" intLanes=":AC_0_0" shape="510.40,304.43,0.67 510.40,301.23,0.67 510.40,304.43,0.67">
        <request index="0" response="0" foes="0" cont="0"/>
    </junction>
    <junction id="B" type="traffic_light" x="511.67" y="219.37" z="-3.16" incLanes="BA2B_0 BA2B_1 BA2B_2 BA2B_3 BB2B_0 BB2B_1 BB2B_2 BB2B_3 BC2B_0 BC2B_1 BC2B_2 BC2B_3 TL2B_0 TL2B_1 TL2B_2 TL2B_3" intLanes=":B_0_0 :B_1_0 :B_1_1 :B_1_2 :B_1_3 :B_24_0 :B_6_0 :B_7_0 :B_7_1 :B_7_2 :B_7_3 :B_25_0 :B_12_0 :B_13_0 :B_13_1 :B_13_2 :B_13_3 :B_26_0 :B_18_0 :B_19_0 :B_19_1 :B_19_2 :B_19_3 :B_27_0" shape="498.87,236.17,-3.16 524.47,236.17,-3.16 524.91,233.95,-3.16 525.47,233.17,-3.16 526.25,232.61,-3.16 527.25,232.28,-3.16 528.47,232.17,-3.16 528.47,206.57,-3.16 526.25,206.12,-3.16 525.47,205.57,-3.16 524.91,204.79,-3.16 524.58,203.79,-3.16 524.47,202.57,-3.16 498.87,202.57,-3.16 498.42,204.79,-3.16 497.87,205.57,-3.16 497.09,206.12,-3.16 496.09,206.46,-3.16 494.87,206.57,-3.16 494.87,232.17,-3.16 497.09,232.61,-3.16 497.87,233.17,-3.16 498.42,233.95,-3.16 498.76,234.95,-3.16">
        <request index="0"  response="000000000000000000000000" foes="000000000000011110000000" cont="0"/>
        <request index="1"  response="100000000000100000000000" foes="111111100000111110000000" cont="0"/>
        <request index="2"  response="100000000000100000000000" foes="111111100000111110000000" cont="0"/>
        <request index="3"  response="100000000000100000000000" foes="111111100000111110000000" cont="0"/>
        <request index="4"  response="100000000000100000000000" foes="111111100000111110000000" cont="0"/>
        <request index="5"  response="100000011110100000000000" foes="111110011110111110000000" cont="1"/>
        <request index="6"  response="000000011110000000000000" foes="000000011110000000000000" cont="0"/>
        <request index="7"  response="000000111110000000111111" foes="100000111110000000111111" cont="0"/>
        <request index="8"  response="000000111110000000111111" foes="100000111110000000111111" cont="0"/>
        <request index="9"  response="000000111110000000111111" foes="100000111110000000111111" cont="0"/>
        <request index="10" response="000000111110000000111111" foes="100000111110000000111111" cont="0"/>
        <request index="11" response="011110111110000000111110" foes="011110111110000000111110" cont="1"/>
        <request index="12" response="000000000000000000000000" foes="011110000000000000000000" cont="0"/>
        <request index="13" response="100000000000100000000000" foes="111110000000111111100000" cont="0"/>
        <request index="14" response="100000000000100000000000" foes="111110000000111111100000" cont="0"/>
        <request index="15" response="100000000000100000000000" foes="111110000000111111100000" cont="0"/>
        <request index="16" response="100000000000100000000000" foes="111110000000111111100000" cont="0"/>
        <request index="17" response="100000000000100000011110" foes="111110000000111110011110" cont="1"/>
        <request index="18" response="000000000000000000011110" foes="000000000000000000011110" cont="0"/>
        <request index="19" response="000000111111000000111110" foes="000000111111100000111110" cont="0"/>
        <request index="20" response="000000111111000000111110" foes="000000111111100000111110" cont="0"/>
        <request index="21" response="000000111111000000111110" foes="000000111111100000111110" cont="0"/>
        <request index="22" response="000000111111000000111110" foes="000000111111100000111110" cont="0"/>
        <request index="23" response="000000111110011110111110" foes="000000111110011110111110" cont="1"/>
    </junction>
    <junction id="BA" type="traffic_light" x="511.67" y="305.70" z="-3.16" incLanes="B2BA_0 B2BA_1 B2BA_2 B2BA_3" intLanes=":BA_0_0" shape="511.67,305.70,-3.16 524.47,305.70,-3.16 511.67,305.70,-3.16">
        <request index="0" response="0" foes="0" cont="0"/>
    </junction>
    <junction id="BB" type="traffic_light" x="598.00" y="219.37" z="-3.16" incLanes="B2BB_0 B2BB_1 B2BB_2 B2BB_3" intLanes=":BB_0_0" shape="598.00,219.37,-3.16 598.00,206.57,-3.16 598.00,219.37,-3.16">
        <request index="0" response="0" foes="0" cont="0"/>
    </junction>
    <junction id="BC" type="traffic_light" x="511.67" y="133.03" z="-3.16" incLanes="B2BC_0 B2BC_1 B2BC_2 B2BC_3" intLanes=":BC_0_0" shape="511.67,133.03,-3.16 498.87,133.03,-3.16 511.67,133.03,-3.16">
        <request index="0" response="0" foes="0" cont="0"/>
    </junction>
    <junction id="C" type="traffic_light" x="425.33" y="109.68" z="1.14" incLanes="TL2C_0 CA2C_0 CB2C_0 CC2C_0" intLanes=":C_0_0 :C_1_0 :C_2_0 :C_3_0 :C_4_0 :C_5_0 :C_6_0 :C_7_0" shape="422.13,116.88,1.14 428.53,116.88,1.14 428.98,114.66,1.14 429.53,113.88,1.14 430.31,113.33,1.14 431.31,112.99,1.14 432.53,112.88,1.14 432.53,106.48,1.14 430.31,106.04,1.14 429.53,105.48,1.14 428.98,104.71,1.14 428.65,103.71,1.14 428.53,102.48,1.14 422.13,102.48,1.14 421.69,104.71,1.14 421.13,105.48,1.14 420.36,106.04,1.14 419.36,106.37,1.14 418.13,106.48,1.14 418.13,112.88,1.14 420.36,113.33,1.14 421.13,113.88,1.14 421.69,114.66,1.14 422.02,115.66,1.14">
        <request index="0" response="00000000" foes="00001000" cont="0"/>
        <request index="1" response="00000000" foes="11001000" cont="0"/>
        <request index="2" response="00100000" foes="00100000" cont="0"/>
        <request index="3" response="00100011" foes="00100011" cont="0"/>
        <request index="4" response="00000000" foes="10000000" cont="0"/>
        <request index="5" response="00000000" foes="10001100" cont="0"/>
        <request index="6" response="00000010" foes="00000010" cont="0"/>
        <request index="7" response="00110010" foes="00110010" cont="0"/>
    </junction>
    <junction id="CA" type="traffic_light" x="535.02" y="109.68" z="1.14" incLanes="C2CA_0" intLanes=":CA_0_0" shape="535.02,109.68,1.14 535.02,106.48,1.14 535.02,109.68,1.14">
        <request index="0" response="0" foes="0" cont="0"/>
    </junction>
    <junction id="CB" type="traffic_light" x="425.33" y="0.00" z="1.14" incLanes="C2CB_0" intLanes=":CB_0_0" shape="425.33,0.00,1.14 422.13,0.00,1.14 425.33,0.00,1.14">
        <request index="0" response="0" foes="0" cont="0"/>
    </junction>
    <junction id="CC" type="traffic_light" x="315.65" y="109.68" z="1.14" incLanes="C2CC_0" intLanes=":CC_0_0" shape="315.65,109.68,1.14 315.65,112.88,1.14 315.65,109.68,1.14">
        <request index="0" response="0" foes="0" cont="0"/>
    </junction>
    <junction id="C_intern" type="priority" x="425.33" y="169.37" z="0.52" incLanes="C2TL_0" intLanes=":C_intern_0_0 :C_intern_0_1" shape="425.33,173.37,0.52 431.73,173.37,0.52 430.91,170.34,0.52 429.36,168.40,0.52 428.77,167.16,0.52 428.53,165.37,0.52 425.33,165.37,0.52">
        <request index="0" response="00" foes="00" cont="0"/>
        <request index="1" response="00" foes="00" cont="0"/>
    </junction>
    <junction id="D" type="traffic_light" x="212.67" y="219.37" z="2.79" incLanes="DC2D_0 DC2D_1 TL2D_0 TL2D_1 DA2D_0 DA2D_1 DB2D_0 DB2D_1" intLanes=":D_0_0 :D_1_0 :D_1_1 :D_16_0 :D_4_0 :D_5_0 :D_5_1 :D_17_0 :D_8_0 :D_9_0 :D_9_1 :D_18_0 :D_12_0 :D_13_0 :D_13_1 :D_19_0" shape="206.27,236.17,2.79 225.47,236.17,2.79 225.58,232.99,2.79 225.91,230.39,2.79 226.47,228.37,2.79 227.25,226.92,2.79 228.25,226.06,2.79 229.47,225.77,2.79 229.47,206.57,2.79 226.29,206.46,2.79 223.69,206.12,2.79 221.67,205.57,2.79 220.22,204.79,2.79 219.36,203.79,2.79 219.07,202.57,2.79 199.87,202.57,2.79 199.76,205.75,2.79 199.42,208.35,2.79 198.87,210.37,2.79 198.09,211.81,2.79 197.09,212.68,2.79 195.87,212.97,2.79 195.87,232.17,2.79 199.05,232.28,2.79 201.65,232.61,2.79 203.67,233.17,2.79 205.11,233.95,2.79 205.98,234.95,2.79">
        <request index="0"  response="0000000000000000" foes="0000000001100000" cont="0"/>
        <request index="1"  response="1000000000000000" foes="1111100001100000" cont="0"/>
        <request index="2"  response="1000000000000000" foes="1111100001100000" cont="0"/>
        <request index="3"  response="1000011010000000" foes="1000011011100000" cont="1"/>
        <request index="4"  response="0000011000000000" foes="0000011000000000" cont="0"/>
        <request index="5"  response="0000011000001111" foes="1000011000001111" cont="0"/>
        <request index="6"  response="0000011000001111" foes="1000011000001111" cont="0"/>
        <request index="7"  response="0110111000001000" foes="0110111000001000" cont="1"/>
        <request index="8"  response="0000000000000000" foes="0110000000000000" cont="0"/>
        <request index="9"  response="0000000010000000" foes="0110000011111000" cont="0"/>
        <request index="10" response="0000000010000000" foes="0110000011111000" cont="0"/>
        <request index="11" response="1000000010000110" foes="1110000010000110" cont="1"/>
        <request index="12" response="0000000000000110" foes="0000000000000110" cont="0"/>
        <request index="13" response="0000111100000110" foes="0000111110000110" cont="0"/>
        <request index="14" response="0000111100000110" foes="0000111110000110" cont="0"/>
        <request index="15" response="0000100001101110" foes="0000100001101110" cont="1"/>
    </junction>
    <junction id="DA" type="traffic_light" x="212.67" y="6.70" z="2.79" incLanes="D2DA_0 D2DA_1 D2DA_2 D2DA_3" intLanes=":DA_0_0" shape="212.67,6.70,2.79 199.87,6.70,2.79 212.67,6.70,2.79">
        <request index="0" response="0" foes="0" cont="0"/>
    </junction>
    <junction id="DB" type="traffic_light" x="0.00" y="219.37" z="2.79" incLanes="D2DB_0 D2DB_1 D2DB_2 D2DB_3" intLanes=":DB_0_0" shape="-0.00,219.37,2.79 -0.00,232.17,2.79 -0.00,219.37,2.79">
        <request index="0" response="0" foes="0" cont="0"/>
    </junction>
    <junction id="DC" type="traffic_light" x="212.67" y="432.03" z="2.79" incLanes="D2DC_0 D2DC_1 D2DC_2 D2DC_3" intLanes=":DC_0_0" shape="212.67,432.03,2.79 225.47,432.03,2.79 212.67,432.03,2.79">
        <request index="0" response="0" foes="0" cont="0"/>
    </junction>
    <junction id="TL" type="traffic_light_right_on_red" x="425.33" y="219.37" incLanes="A2TL_0 B2TL_0 B2TL_1 B2TL_2 B2TL_3 C2TL_intern_0 C2TL_intern_1 D2TL_0 D2TL_1 D2TL_2 D2TL_3" intLanes=":TL_0_0 :TL_1_0 :TL_2_0 :TL_2_1 :TL_2_2 :TL_2_3 :TL_16_0 :TL_7_0 :TL_8_0 :TL_17_0 :TL_10_0 :TL_11_0 :TL_11_1 :TL_11_2 :TL_11_3 :TL_18_0" shape="422.13,236.17 428.53,236.17 429.33,233.95 430.33,233.17 431.73,232.61 433.53,232.28 435.73,232.17 435.73,206.57 433.51,206.12 432.73,205.57 432.18,204.79 431.85,203.79 431.73,202.57 422.13,202.57 421.69,204.79 421.13,205.57 420.36,206.12 419.36,206.46 418.13,206.57 418.13,225.77 420.36,226.92 421.13,228.37 421.69,230.39 422.02,232.99">
        <request index="0"  response="1111110001111100" foes="1111111001111100" cont="0"/>
        <request index="1"  response="0000000100000000" foes="1000000100000000" cont="0"/>
        <request index="2"  response="0000001000000000" foes="1000001100000001" cont="0"/>
        <request index="3"  response="0000001000110000" foes="1000001100110001" cont="0"/>
        <request index="4"  response="0000001000100000" foes="1000001100101001" cont="0"/>
        <request index="5"  response="0000001000000000" foes="1000001100011001" cont="0"/>
        <request index="6"  response="0111111000000000" foes="0111111100000001" cont="1"/>
        <request index="7"  response="0111100000000000" foes="0111100000000000" cont="0"/>
        <request index="8"  response="1111100001111110" foes="1111100001111110" cont="0"/>
        <request index="9"  response="1111100001111101" foes="1111100001111101" cont="1"/>
        <request index="10" response="0000000000000001" foes="0000000001000001" cont="0"/>
        <request index="11" response="0000001000000000" foes="0000001111000001" cont="0"/>
        <request index="12" response="0000001000000000" foes="0000001111000001" cont="0"/>
        <request index="13" response="0000001000000000" foes="0000001111000001" cont="0"/>
        <request index="14" response="0000001000000000" foes="0000001111000001" cont="0"/>
        <request index="15" response="0000001000111110" foes="0000001100111111" cont="1"/>
    </junction>

    <junction id=":B_24_0" type="internal" x="510.78" y="231.20" z="-3.16" incLanes=":B_5_0 BC2B_0 BC2B_1 BC2B_2 BC2B_3" intLanes=":B_7_0 :B_7_1 :B_7_2 :B_7_3 :B_11_0 :B_12_0 :B_13_0 :B_13_1 :B_13_2 :B_13_3 :B_19_0 :B_19_1 :B_19_2 :B_19_3 :B_23_0"/>
    <junction id=":B_25_0" type="internal" x="523.51" y="220.26" z="-3.16" incLanes=":B_11_0 TL2B_0 TL2B_1 TL2B_2 TL2B_3" intLanes=":B_1_0 :B_1_1 :B_1_2 :B_1_3 :B_5_0 :B_13_0 :B_13_1 :B_13_2 :B_13_3 :B_17_0 :B_18_0 :B_19_0 :B_19_1 :B_19_2 :B_19_3"/>
    <junction id=":B_26_0" type="internal" x="512.56" y="207.53" z="-3.16" incLanes=":B_17_0 BA2B_0 BA2B_1 BA2B_2 BA2B_3" intLanes=":B_0_0 :B_1_0 :B_1_1 :B_1_2 :B_1_3 :B_7_0 :B_7_1 :B_7_2 :B_7_3 :B_11_0 :B_19_0 :B_19_1 :B_19_2 :B_19_3 :B_23_0"/>
    <junction id=":B_27_0" type="internal" x="499.83" y="218.48" z="-3.16" incLanes=":B_23_0 BB2B_0 BB2B_1 BB2B_2 BB2B_3" intLanes=":B_1_0 :B_1_1 :B_1_2 :B_1_3 :B_5_0 :B_6_0 :B_7_0 :B_7_1 :B_7_2 :B_7_3 :B_13_0 :B_13_1 :B_13_2 :B_13_3 :B_17_0"/>
    <junction id=":D_16_0" type="internal" x="216.15" y="222.08" z="2.79" incLanes=":D_3_0 DA2D_0 DA2D_1" intLanes=":D_5_0 :D_5_1 :D_7_0 :D_8_0 :D_9_0 :D_9_1 :D_13_0 :D_13_1 :D_15_0"/>
    <junction id=":D_17_0" type="internal" x="215.38" y="215.88" z="2.79" incLanes=":D_7_0 DB2D_0 DB2D_1" intLanes=":D_1_0 :D_1_1 :D_3_0 :D_9_0 :D_9_1 :D_11_0 :D_12_0 :D_13_0 :D_13_1"/>
    <junction id=":D_18_0" type="internal" x="209.18" y="216.66" z="2.79" incLanes=":D_11_0 DC2D_0 DC2D_1" intLanes=":D_0_0 :D_1_0 :D_1_1 :D_5_0 :D_5_1 :D_7_0 :D_13_0 :D_13_1 :D_15_0"/>
    <junction id=":D_19_0" type="internal" x="209.96" y="222.85" z="2.79" incLanes=":D_15_0 TL2D_0 TL2D_1" intLanes=":D_1_0 :D_1_1 :D_3_0 :D_4_0 :D_5_0 :D_5_1 :D_9_0 :D_9_1 :D_11_0"/>
    <junction id=":TL_16_0" type="internal" x="432.44" y="220.25" z="0.02" incLanes=":TL_6_0 D2TL_0 D2TL_1 D2TL_2 D2TL_3" intLanes=":TL_0_0 :TL_8_0 :TL_9_0 :TL_10_0 :TL_11_0 :TL_11_1 :TL_11_2 :TL_11_3"/>
    <junction id=":TL_17_0" type="internal" x="426.25" y="211.08" z="0.14" incLanes=":TL_9_0 A2TL_0" intLanes=":TL_0_0 :TL_2_0 :TL_2_1 :TL_2_2 :TL_2_3 :TL_6_0 :TL_11_0 :TL_11_1 :TL_11_2 :TL_11_3 :TL_15_0"/>
    <junction id=":TL_18_0" type="internal" x="420.60" y="218.50" z="0.11" incLanes=":TL_15_0 B2TL_0 B2TL_1 B2TL_2 B2TL_3" intLanes=":TL_0_0 :TL_1_0 :TL_2_0 :TL_2_1 :TL_2_2 :TL_2_3 :TL_8_0 :TL_9_0"/>

    <connection from="A2AA" to="AA2A" fromLane="0" toLane="0" via=":AA_0_0" tl="AA" linkIndex="0" dir="t" state="O"/>
    <connection from="A2AB" to="AB2A" fromLane="0" toLane="0" via=":AB_0_0" tl="AB" linkIndex="0" dir="t" state="O"/>
    <connection from="A2AC" to="AC2A" fromLane="0" toLane="0" via=":AC_0_0" tl="AC" linkIndex="0" dir="t" state="O"/>
    <connection from="A2TL" to="TL2C" fromLane="0" toLane="0" via=":TL_0_0" tl="TL" linkIndex="0" dir="s" state="o"/>
    <connection from="AA2A" to="A2TL" fromLane="0" toLane="0" via=":A_6_0" tl="A" linkIndex="6" dir="r" state="o"/>
    <connection from="AA2A" to="A2AC" fromLane="0" toLane="0" via=":A_7_0" tl="A" linkIndex="7" dir="s" state="o"/>
    <connection from="AB2A" to="A2AA" fromLane="0" toLane="0" via=":A_0_0" tl="A" linkIndex="0" dir="r" state="O"/>
    <connection from="AB2A" to="A2TL" fromLane="0" toLane="0" via=":A_1_0" tl="A" linkIndex="1" dir="s" state="O"/>
    <connection from="AC2A" to="A2AB" fromLane="0" toLane="0" via=":A_2_0" tl="A" linkIndex="2" dir="r" state="o"/>
    <connection from="AC2A" to="A2AA" fromLane="0" toLane="0" via=":A_3_0" tl="A" linkIndex="3" dir="s" state="o"/>
    <connection from="B2BA" to="BA2B" fromLane="3" toLane="3" via=":BA_0_0" tl="BA" linkIndex="0" dir="t" state="O"/>
    <connection from="B2BB" to="BB2B" fromLane="3" toLane="3" via=":BB_0_0" tl="BB" linkIndex="0" dir="t" state="O"/>
    <connection from="B2BC" to="BC2B" fromLane="3" toLane="3" via=":BC_0_0" tl="BC" linkIndex="0" dir="t" state="O"/>
    <connection from="B2TL" to="TL2A" fromLane="0" toLane="0" via=":TL_1_0" tl="TL" linkIndex="1" dir="r" state="O"/>
    <connection from="B2TL" to="TL2D" fromLane="0" toLane="0" via=":TL_2_0" tl="TL" linkIndex="2" dir="s" state="O"/>
    <connection from="B2TL" to="TL2D" fromLane="1" toLane="1" via=":TL_2_1" tl="TL" linkIndex="3" dir="s" state="o"/>
    <connection from="B2TL" to="TL2D" fromLane="2" toLane="1" via=":TL_2_2" tl="TL" linkIndex="4" dir="s" state="o"/>
    <connection from="B2TL" to="TL2D" fromLane="3" toLane="1" via=":TL_2_3" tl="TL" linkIndex="5" dir="s" state="O"/>
    <connection from="B2TL" to="TL2C" fromLane="3" toLane="0" via=":TL_6_0" tl="TL" linkIndex="6" dir="l" state="o"/>
    <connection from="BA2B" to="B2TL" fromLane="0" toLane="0" via=":B_0_0" tl="B" linkIndex="0" dir="r" state="O"/>
    <connection from="BA2B" to="B2BC" fromLane="0" toLane="0" via=":B_1_0" tl="B" linkIndex="1" dir="s" state="O"/>
    <connection from="BA2B" to="B2BC" fromLane="1" toLane="1" via=":B_1_1" tl="B" linkIndex="2" dir="s" state="O"/>
    <connection from="BA2B" to="B2BC" fromLane="2" toLane="2" via=":B_1_2" tl="B" linkIndex="3" dir="s" state="O"/>
    <connection from="BA2B" to="B2BC" fromLane="3" toLane="3" via=":B_1_3" tl="B" linkIndex="4" dir="s" state="O"/>
    <connection from="BA2B" to="B2BB" fromLane="3" toLane="3" via=":B_5_0" tl="B" linkIndex="5" dir="l" state="o"/>
    <connection from="BB2B" to="B2BA" fromLane="0" toLane="0" via=":B_6_0" tl="B" linkIndex="6" dir="r" state="o"/>
    <connection from="BB2B" to="B2TL" fromLane="0" toLane="0" via=":B_7_0" tl="B" linkIndex="7" dir="s" state="o"/>
    <connection from="BB2B" to="B2TL" fromLane="1" toLane="1" via=":B_7_1" tl="B" linkIndex="8" dir="s" state="o"/>
    <connection from="BB2B" to="B2TL" fromLane="2" toLane="2" via=":B_7_2" tl="B" linkIndex="9" dir="s" state="o"/>
    <connection from="BB2B" to="B2TL" fromLane="3" toLane="3" via=":B_7_3" tl="B" linkIndex="10" dir="s" state="o"/>
    <connection from="BB2B" to="B2BC" fromLane="3" toLane="3" via=":B_11_0" tl="B" linkIndex="11" dir="l" state="o"/>
    <connection from="BC2B" to="B2BB" fromLane="0" toLane="0" via=":B_12_0" tl="B" linkIndex="12" dir="r" state="O"/>
    <connection from="BC2B" to="B2BA" fromLane="0" toLane="0" via=":B_13_0" tl="B" linkIndex="13" dir="s" state="O"/>
    <connection from="BC2B" to="B2BA" fromLane="1" toLane="1" via=":B_13_1" tl="B" linkIndex="14" dir="s" state="O"/>
    <connection from="BC2B" to="B2BA" fromLane="2" toLane="2" via=":B_13_2" tl="B" linkIndex="15" dir="s" state="O"/>
    <connection from="BC2B" to="B2BA" fromLane="3" toLane="3" via=":B_13_3" tl="B" linkIndex="16" dir="s" state="O"/>
    <connection from="BC2B" to="B2TL" fromLane="3" toLane="3" via=":B_17_0" tl="B" linkIndex="17" dir="l" state="o"/>
    <connection from="C2CA" to="CA2C" fromLane="0" toLane="0" via=":CA_0_0" tl="CA" linkIndex="0" dir="t" state="O"/>
    <connection from="C2CB" to="CB2C" fromLane="0" toLane="0" via=":CB_0_0" tl="CB" linkIndex="0" dir="t" state="O"/>
    <connection from="C2CC" to="CC2C" fromLane="0" toLane="0" via=":CC_0_0" tl="CC" linkIndex="0" dir="t" state="O"/>
    <connection from="C2TL" to="C2TL_intern" fromLane="0" toLane="0" via=":C_intern_0_0" dir="s" state="M"/>
    <connection from="C2TL" to="C2TL_intern" fromLane="0" toLane="1" via=":C_intern_0_1" dir="s" state="M"/>
    <connection from="C2TL_intern" to="TL2B" fromLane="0" toLane="0" via=":TL_7_0" tl="TL" linkIndex="7" dir="r" state="o"/>
    <connection from="C2TL_intern" to="TL2A" fromLane="0" toLane="0" via=":TL_8_0" tl="TL" linkIndex="8" dir="s" state="o"/>
    <connection from="C2TL_intern" to="TL2D" fromLane="1" toLane="1" via=":TL_9_0" tl="TL" linkIndex="9" dir="l" state="o"/>
    <connection from="CA2C" to="C2TL" fromLane="0" toLane="0" via=":C_2_0" tl="C" linkIndex="2" dir="r" state="o"/>
    <connection from="CA2C" to="C2CC" fromLane="0" toLane="0" via=":C_3_0" tl="C" linkIndex="3" dir="s" state="o"/>
    <connection from="CB2C" to="C2CA" fromLane="0" toLane="0" via=":C_4_0" tl="C" linkIndex="4" dir="r" state="O"/>
    <connection from="CB2C" to="C2TL" fromLane="0" toLane="0" via=":C_5_0" tl="C" linkIndex="5" dir="s" state="O"/>
    <connection from="CC2C" to="C2CB" fromLane="0" toLane="0" via=":C_6_0" tl="C" linkIndex="6" dir="r" state="o"/>
    <connection from="CC2C" to="C2CA" fromLane="0" toLane="0" via=":C_7_0" tl="C" linkIndex="7" dir="s" state="o"/>
    <connection from="D2DA" to="DA2D" fromLane="3" toLane="1" via=":DA_0_0" tl="DA" linkIndex="0" dir="t" state="O"/>
    <connection from="D2DB" to="DB2D" fromLane="3" toLane="1" via=":DB_0_0" tl="DB" linkIndex="0" dir="t" state="O"/>
    <connection from="D2DC" to="DC2D" fromLane="3" toLane="1" via=":DC_0_0" tl="DC" linkIndex="0" dir="t" state="O"/>
    <connection from="D2TL" to="TL2C" fromLane="0" toLane="0" via=":TL_10_0" tl="TL" linkIndex="10" dir="r" state="O"/>
    <connection from="D2TL" to="TL2B" fromLane="0" toLane="0" via=":TL_11_0" tl="TL" linkIndex="11" dir="s" state="O"/>
    <connection from="D2TL" to="TL2B" fromLane="1" toLane="1" via=":TL_11_1" tl="TL" linkIndex="12" dir="s" state="O"/>
    <connection from="D2TL" to="TL2B" fromLane="2" toLane="2" via=":TL_11_2" tl="TL" linkIndex="13" dir="s" state="O"/>
    <connection from="D2TL" to="TL2B" fromLane="3" toLane="3" via=":TL_11_3" tl="TL" linkIndex="14" dir="s" state="O"/>
    <connection from="D2TL" to="TL2A" fromLane="3" toLane="0" via=":TL_15_0" tl="TL" linkIndex="15" dir="l" state="o"/>
    <connection from="DA2D" to="D2TL" fromLane="0" toLane="0" via=":D_8_0" tl="D" linkIndex="8" dir="r" state="O"/>
    <connection from="DA2D" to="D2DC" fromLane="0" toLane="0" via=":D_9_0" tl="D" linkIndex="9" dir="s" state="O"/>
    <connection from="DA2D" to="D2DC" fromLane="1" toLane="1" via=":D_9_1" tl="D" linkIndex="10" dir="s" state="O"/>
    <connection from="DA2D" to="D2DB" fromLane="1" toLane="3" via=":D_11_0" tl="D" linkIndex="11" dir="l" state="o"/>
    <connection from="DB2D" to="D2DA" fromLane="0" toLane="0" via=":D_12_0" tl="D" linkIndex="12" dir="r" state="o"/>
    <connection from="DB2D" to="D2TL" fromLane="0" toLane="0" via=":D_13_0" tl="D" linkIndex="13" dir="s" state="o"/>
    <connection from="DB2D" to="D2TL" fromLane="1" toLane="1" via=":D_13_1" tl="D" linkIndex="14" dir="s" state="o"/>
    <connection from="DB2D" to="D2DC" fromLane="1" toLane="3" via=":D_15_0" tl="D" linkIndex="15" dir="l" state="o"/>
    <connection from="DC2D" to="D2DB" fromLane="0" toLane="0" via=":D_0_0" tl="D" linkIndex="0" dir="r" state="O"/>
    <connection from="DC2D" to="D2DA" fromLane="0" toLane="0" via=":D_1_0" tl="D" linkIndex="1" dir="s" state="O"/>
    <connection from="DC2D" to="D2DA" fromLane="1" toLane="1" via=":D_1_1" tl="D" linkIndex="2" dir="s" state="O"/>
    <connection from="DC2D" to="D2TL" fromLane="1" toLane="3" via=":D_3_0" tl="D" linkIndex="3" dir="l" state="o"/>
    <connection from="TL2A" to="A2AC" fromLane="0" toLane="0" via=":A_4_0" tl="A" linkIndex="4" dir="r" state="O"/>
    <connection from="TL2A" to="A2AB" fromLane="0" toLane="0" via=":A_5_0" tl="A" linkIndex="5" dir="s" state="O"/>
    <connection from="TL2B" to="B2BC" fromLane="0" toLane="0" via=":B_18_0" tl="B" linkIndex="18" dir="r" state="o"/>
    <connection from="TL2B" to="B2BB" fromLane="0" toLane="0" via=":B_19_0" tl="B" linkIndex="19" dir="s" state="o"/>
    <connection from="TL2B" to="B2BB" fromLane="1" toLane="1" via=":B_19_1" tl="B" linkIndex="20" dir="s" state="o"/>
    <connection from="TL2B" to="B2BB" fromLane="2" toLane="2" via=":B_19_2" tl="B" linkIndex="21" dir="s" state="o"/>
    <connection from="TL2B" to="B2BB" fromLane="3" toLane="3" via=":B_19_3" tl="B" linkIndex="22" dir="s" state="o"/>
    <connection from="TL2B" to="B2BA" fromLane="3" toLane="3" via=":B_23_0" tl="B" linkIndex="23" dir="l" state="o"/>
    <connection from="TL2C" to="C2CC" fromLane="0" toLane="0" via=":C_0_0" tl="C" linkIndex="0" dir="r" state="O"/>
    <connection from="TL2C" to="C2CB" fromLane="0" toLane="0" via=":C_1_0" tl="C" linkIndex="1" dir="s" state="O"/>
    <connection from="TL2D" to="D2DC" fromLane="0" toLane="0" via=":D_4_0" tl="D" linkIndex="4" dir="r" state="o"/>
    <connection from="TL2D" to="D2DB" fromLane="0" toLane="0" via=":D_5_0" tl="D" linkIndex="5" dir="s" state="o"/>
    <connection from="TL2D" to="D2DB" fromLane="1" toLane="1" via=":D_5_1" tl="D" linkIndex="6" dir="s" state="o"/>
    <connection from="TL2D" to="D2DA" fromLane="1" toLane="3" via=":D_7_0" tl="D" linkIndex="7" dir="l" state="o"/>

    <connection from=":A_0" to="A2AA" fromLane="0" toLane="0" dir="r" state="M"/>
    <connection from=":A_1" to="A2TL" fromLane="0" toLane="0" dir="s" state="M"/>
    <connection from=":A_2" to="A2AB" fromLane="0" toLane="0" dir="r" state="M"/>
    <connection from=":A_3" to="A2AA" fromLane="0" toLane="0" dir="s" state="M"/>
    <connection from=":A_4" to="A2AC" fromLane="0" toLane="0" dir="r" state="M"/>
    <connection from=":A_5" to="A2AB" fromLane="0" toLane="0" dir="s" state="M"/>
    <connection from=":A_6" to="A2TL" fromLane="0" toLane="0" dir="r" state="M"/>
    <connection from=":A_7" to="A2AC" fromLane="0" toLane="0" dir="s" state="M"/>
    <connection from=":AA_0" to="AA2A" fromLane="0" toLane="0" dir="t" state="M"/>
    <connection from=":AB_0" to="AB2A" fromLane="0" toLane="0" dir="t" state="M"/>
    <connection from=":AC_0" to="AC2A" fromLane="0" toLane="0" dir="t" state="M"/>
    <connection from=":B_0" to="B2TL" fromLane="0" toLane="0" dir="r" state="M"/>
    <connection from=":B_1" to="B2BC" fromLane="0" toLane="0" dir="s" state="M"/>
    <connection from=":B_1" to="B2BC" fromLane="1" toLane="1" dir="s" state="M"/>
    <connection from=":B_1" to="B2BC" fromLane="2" toLane="2" dir="s" state="M"/>
    <connection from=":B_1" to="B2BC" fromLane="3" toLane="3" dir="s" state="M"/>
    <connection from=":B_5" to="B2BB" fromLane="0" toLane="3" via=":B_24_0" dir="l" state="m"/>
    <connection from=":B_24" to="B2BB" fromLane="0" toLane="3" dir="l" state="M"/>
    <connection from=":B_6" to="B2BA" fromLane="0" toLane="0" dir="r" state="M"/>
    <connection from=":B_7" to="B2TL" fromLane="0" toLane="0" dir="s" state="M"/>
    <connection from=":B_7" to="B2TL" fromLane="1" toLane="1" dir="s" state="M"/>
    <connection from=":B_7" to="B2TL" fromLane="2" toLane="2" dir="s" state="M"/>
    <connection from=":B_7" to="B2TL" fromLane="3" toLane="3" dir="s" state="M"/>
    <connection from=":B_11" to="B2BC" fromLane="0" toLane="3" via=":B_25_0" dir="l" state="m"/>
    <connection from=":B_25" to="B2BC" fromLane="0" toLane="3" dir="l" state="M"/>
    <connection from=":B_12" to="B2BB" fromLane="0" toLane="0" dir="r" state="M"/>
    <connection from=":B_13" to="B2BA" fromLane="0" toLane="0" dir="s" state="M"/>
    <connection from=":B_13" to="B2BA" fromLane="1" toLane="1" dir="s" state="M"/>
    <connection from=":B_13" to="B2BA" fromLane="2" toLane="2" dir="s" state="M"/>
    <connection from=":B_13" to="B2BA" fromLane="3" toLane="3" dir="s" state="M"/>
    <connection from=":B_17" to="B2TL" fromLane="0" toLane="3" via=":B_26_0" dir="l" state="m"/>
    <connection from=":B_26" to="B2TL" fromLane="0" toLane="3" dir="l" state="M"/>
    <connection from=":B_18" to="B2BC" fromLane="0" toLane="0" dir="r" state="M"/>
    <connection from=":B_19" to="B2BB" fromLane="0" toLane="0" dir="s" state="M"/>
    <connection from=":B_19" to="B2BB" fromLane="1" toLane="1" dir="s" state="M"/>
    <connection from=":B_19" to="B2BB" fromLane="2" toLane="2" dir="s" state="M"/>
    <connection from=":B_19" to="B2BB" fromLane="3" toLane="3" dir="s" state="M"/>
    <connection from=":B_23" to="B2BA" fromLane="0" toLane="3" via=":B_27_0" dir="l" state="m"/>
    <connection from=":B_27" to="B2BA" fromLane="0" toLane="3" dir="l" state="M"/>
    <connection from=":BA_0" to="BA2B" fromLane="0" toLane="3" dir="t" state="M"/>
    <connection from=":BB_0" to="BB2B" fromLane="0" toLane="3" dir="t" state="M"/>
    <connection from=":BC_0" to="BC2B" fromLane="0" toLane="3" dir="t" state="M"/>
    <connection from=":C_0" to="C2CC" fromLane="0" toLane="0" dir="r" state="M"/>
    <connection from=":C_1" to="C2CB" fromLane="0" toLane="0" dir="s" state="M"/>
    <connection from=":C_2" to="C2TL" fromLane="0" toLane="0" dir="r" state="M"/>
    <connection from=":C_3" to="C2CC" fromLane="0" toLane="0" dir="s" state="M"/>
    <connection from=":C_4" to="C2CA" fromLane="0" toLane="0" dir="r" state="M"/>
    <connection from=":C_5" to="C2TL" fromLane="0" toLane="0" dir="s" state="M"/>
    <connection from=":C_6" to="C2CB" fromLane="0" toLane="0" dir="r" state="M"/>
    <connection from=":C_7" to="C2CA" fromLane="0" toLane="0" dir="s" state="M"/>
    <connection from=":CA_0" to="CA2C" fromLane="0" toLane="0" dir="t" state="M"/>
    <connection from=":CB_0" to="CB2C" fromLane="0" toLane="0" dir="t" state="M"/>
    <connection from=":CC_0" to="CC2C" fromLane="0" toLane="0" dir="t" state="M"/>
    <connection from=":C_intern_0" to="C2TL_intern" fromLane="0" toLane="0" dir="s" state="M"/>
    <connection from=":C_intern_0" to="C2TL_intern" fromLane="1" toLane="1" dir="s" state="M"/>
    <connection from=":D_0" to="D2DB" fromLane="0" toLane="0" dir="r" state="M"/>
    <connection from=":D_1" to="D2DA" fromLane="0" toLane="0" dir="s" state="M"/>
    <connection from=":D_1" to="D2DA" fromLane="1" toLane="1" dir="s" state="M"/>
    <connection from=":D_3" to="D2TL" fromLane="0" toLane="3" via=":D_16_0" dir="l" state="m"/>
    <connection from=":D_16" to="D2TL" fromLane="0" toLane="3" dir="l" state="M"/>
    <connection from=":D_4" to="D2DC" fromLane="0" toLane="0" dir="r" state="M"/>
    <connection from=":D_5" to="D2DB" fromLane="0" toLane="0" dir="s" state="M"/>
    <connection from=":D_5" to="D2DB" fromLane="1" toLane="1" dir="s" state="M"/>
    <connection from=":D_7" to="D2DA" fromLane="0" toLane="3" via=":D_17_0" dir="l" state="m"/>
    <connection from=":D_17" to="D2DA" fromLane="0" toLane="3" dir="l" state="M"/>
    <connection from=":D_8" to="D2TL" fromLane="0" toLane="0" dir="r" state="M"/>
    <connection from=":D_9" to="D2DC" fromLane="0" toLane="0" dir="s" state="M"/>
    <connection from=":D_9" to="D2DC" fromLane="1" toLane="1" dir="s" state="M"/>
    <connection from=":D_11" to="D2DB" fromLane="0" toLane="3" via=":D_18_0" dir="l" state="m"/>
    <connection from=":D_18" to="D2DB" fromLane="0" toLane="3" dir="l" state="M"/>
    <connection from=":D_12" to="D2DA" fromLane="0" toLane="0" dir="r" state="M"/>
    <connection from=":D_13" to="D2TL" fromLane="0" toLane="0" dir="s" state="M"/>
    <connection from=":D_13" to="D2TL" fromLane="1" toLane="1" dir="s" state="M"/>
    <connection from=":D_15" to="D2DC" fromLane="0" toLane="3" via=":D_19_0" dir="l" state="m"/>
    <connection from=":D_19" to="D2DC" fromLane="0" toLane="3" dir="l" state="M"/>
    <connection from=":DA_0" to="DA2D" fromLane="0" toLane="1" dir="t" state="M"/>
    <connection from=":DB_0" to="DB2D" fromLane="0" toLane="1" dir="t" state="M"/>
    <connection from=":DC_0" to="DC2D" fromLane="0" toLane="1" dir="t" state="M"/>
    <connection from=":TL_0" to="TL2C" fromLane="0" toLane="0" dir="s" state="M"/>
    <connection from=":TL_1" to="TL2A" fromLane="0" toLane="0" dir="r" state="M"/>
    <connection from=":TL_2" to="TL2D" fromLane="0" toLane="0" dir="s" state="M"/>
    <connection from=":TL_2" to="TL2D" fromLane="1" toLane="1" dir="s" state="M"/>
    <connection from=":TL_2" to="TL2D" fromLane="2" toLane="1" dir="s" state="M"/>
    <connection from=":TL_2" to="TL2D" fromLane="3" toLane="1" dir="s" state="M"/>
    <connection from=":TL_6" to="TL2C" fromLane="0" toLane="0" via=":TL_16_0" dir="l" state="m"/>
    <connection from=":TL_16" to="TL2C" fromLane="0" toLane="0" dir="l" state="M"/>
    <connection from=":TL_7" to="TL2B" fromLane="0" toLane="0" dir="r" state="M"/>
    <connection from=":TL_8" to="TL2A" fromLane="0" toLane="0" dir="s" state="M"/>
    <connection from=":TL_9" to="TL2D" fromLane="0" toLane="1" via=":TL_17_0" dir="l" state="m"/>
    <connection from=":TL_17" to="TL2D" fromLane="0" toLane="1" dir="l" state="M"/>
    <connection from=":TL_10" to="TL2C" fromLane="0" toLane="0" dir="r" state="M"/>
    <connection from=":TL_11" to="TL2B" fromLane="0" toLane="0" dir="s" state="M"/>
    <connection from=":TL_11" to="TL2B" fromLane="1" toLane="1" dir="s" state="M"/>
    <connection from=":TL_11" to="TL2B" fromLane="2" toLane="2" dir="s" state="M"/>
    <connection from=":TL_11" to="TL2B" fromLane="3" toLane="3" dir="s" state="M"/>
    <connection from=":TL_15" to="TL2A" fromLane="0" toLane="0" via=":TL_18_0" dir="l" state="m"/>
    <connection from=":TL_18" to="TL2A" fromLane="0" toLane="0" dir="l" state="M"/>

</net>
