<?xml version="1.0" encoding="UTF-8"?>

<!-- generated on 2022-10-11 17:11:01 by Eclipse SUMO netconvert Version 1.14.1
<configuration xmlns:xsi="http://www.w3.org/2001/XMLSchema-instance" xsi:noNamespaceSchemaLocation="http://sumo.dlr.de/xsd/netconvertConfiguration.xsd">

    <input>
        <node-files value="../data/salt-lake-city/nodes.nod.xml"/>
        <edge-files value="../data/salt-lake-city/edges.edg.xml"/>
        <connection-files value="../data/salt-lake-city/connections.con.xml"/>
    </input>

    <output>
        <output-file value="../data/salt-lake-city/sumo/net/206.net.xml"/>
    </output>

    <tls_building>
        <tls.minor-left.max-speed value="1"/>
    </tls_building>

    <report>
        <verbose value="true"/>
    </report>

</configuration>
-->

<net version="1.9" junctionCornerDetail="5" limitTurnSpeed="5.50" xmlns:xsi="http://www.w3.org/2001/XMLSchema-instance" xsi:noNamespaceSchemaLocation="http://sumo.dlr.de/xsd/net_file.xsd">

    <location netOffset="592.92,280.16" convBoundary="0.00,0.00,1151.63,723.21" origBoundary="-592.92,-280.16,558.70,443.05" projParameter="!"/>

    <edge id=":A_0" function="internal">
        <lane id=":A_0_0" index="0" speed="7.33" length="11.73" shape="591.32,512.09,-1.28 590.77,509.64,-1.28 589.12,507.89,-1.28 586.37,506.84,-1.28 582.52,506.49,-1.28"/>
    </edge>
    <edge id=":A_1" function="internal">
        <lane id=":A_1_0" index="0" speed="20.00" length="21.09" shape="591.32,512.09,-1.28 590.82,508.14,-1.27 589.72,503.56,-1.26 588.62,498.05,-1.24 588.12,491.29,-1.22"/>
    </edge>
    <edge id=":A_2" function="internal">
        <lane id=":A_2_0" index="0" speed="7.33" length="11.73" shape="603.32,503.29,-1.28 600.87,503.84,-1.28 599.12,505.49,-1.28 598.07,508.24,-1.28 597.72,512.09,-1.28"/>
    </edge>
    <edge id=":A_3" function="internal">
        <lane id=":A_3_0" index="0" speed="20.00" length="21.09" shape="603.32,503.29,-1.28 599.37,503.79,-1.28 594.80,504.89,-1.28 589.29,505.99,-1.28 582.52,506.49,-1.28"/>
    </edge>
    <edge id=":A_4" function="internal">
        <lane id=":A_4_0" index="0" speed="7.33" length="11.73" shape="594.52,491.29,-1.22 595.07,493.74,-1.24 596.72,495.49,-1.25 599.47,496.54,-1.26 603.32,496.89,-1.28"/>
    </edge>
    <edge id=":A_5" function="internal">
        <lane id=":A_5_0" index="0" speed="20.00" length="21.09" shape="594.52,491.29,-1.22 595.02,495.24,-1.23 596.12,499.81,-1.25 597.22,505.32,-1.26 597.72,512.09,-1.28"/>
    </edge>
    <edge id=":A_6" function="internal">
        <lane id=":A_6_0" index="0" speed="7.33" length="11.73" shape="582.52,500.09,-1.28 584.97,499.54,-1.27 586.72,497.89,-1.26 587.77,495.14,-1.24 588.12,491.29,-1.22"/>
    </edge>
    <edge id=":A_7" function="internal">
        <lane id=":A_7_0" index="0" speed="20.00" length="21.09" shape="582.52,500.09,-1.28 586.48,499.59,-1.28 591.05,498.49,-1.28 596.56,497.39,-1.28 603.32,496.89,-1.28"/>
    </edge>
    <edge id=":AA_0" function="internal">
        <lane id=":AA_0_0" index="0" speed="3.65" length="4.67" shape="371.40,503.29,-1.28 370.20,502.49,-1.28 369.80,501.69,-1.28 370.20,500.89,-1.28 371.40,500.09,-1.28"/>
    </edge>
    <edge id=":AB_0" function="internal">
        <lane id=":AB_0_0" index="0" speed="3.65" length="4.67" shape="594.52,723.21,-1.28 593.72,724.41,-1.28 592.92,724.81,-1.28 592.12,724.41,-1.28 591.32,723.21,-1.28"/>
    </edge>
    <edge id=":AC_0" function="internal">
        <lane id=":AC_0_0" index="0" speed="3.65" length="4.67" shape="814.45,500.09,-1.28 815.65,500.89,-1.28 816.05,501.69,-1.28 815.65,502.49,-1.28 814.45,503.29,-1.28"/>
    </edge>
    <edge id=":B_0" function="internal">
        <lane id=":B_0_0" index="0" speed="7.33" length="11.73" shape="885.78,383.73,-5.28 883.28,383.49,-5.28 881.11,384.52,-5.28 879.26,386.81,-5.28 877.74,390.37,-5.28"/>
    </edge>
    <edge id=":B_1" function="internal">
        <lane id=":B_1_0" index="0" speed="30.00" length="33.80" shape="885.78,383.73,-5.28 876.87,381.36,-5.28 869.98,380.28,-5.28 862.75,379.08,-5.28 852.84,376.39,-5.28"/>
        <lane id=":B_1_1" index="1" speed="30.00" length="33.80" shape="886.77,380.69,-5.28 877.86,378.32,-5.28 870.97,377.23,-5.28 863.74,376.04,-5.28 853.82,373.35,-5.28"/>
        <lane id=":B_1_2" index="2" speed="30.00" length="33.80" shape="887.76,377.64,-5.28 878.85,375.27,-5.28 871.95,374.19,-5.28 864.73,373.00,-5.28 854.81,370.30,-5.28"/>
    </edge>
    <edge id=":B_4" function="internal">
        <lane id=":B_4_0" index="0" speed="11.36" length="12.06" shape="887.76,377.64,-5.28 880.46,374.06,-5.28 877.88,371.10,-5.28"/>
    </edge>
    <edge id=":B_20" function="internal">
        <lane id=":B_20_0" index="0" speed="11.36" length="17.62" shape="877.88,371.10,-5.28 876.05,369.00,-5.28 874.55,362.47,-5.28 875.94,354.46,-5.28"/>
    </edge>
    <edge id=":B_5" function="internal">
        <lane id=":B_5_0" index="0" speed="7.33" length="11.73" shape="885.07,357.42,-5.28 884.84,359.92,-5.28 885.87,362.10,-5.28 888.16,363.95,-5.28 891.71,365.47,-5.28"/>
    </edge>
    <edge id=":B_6" function="internal">
        <lane id=":B_6_0" index="0" speed="30.00" length="33.80" shape="885.07,357.42,-5.28 882.71,366.33,-5.28 881.62,373.23,-5.28 880.43,380.46,-5.28 877.74,390.37,-5.28"/>
        <lane id=":B_6_1" index="1" speed="30.00" length="33.80" shape="882.03,356.43,-5.28 879.66,365.34,-5.28 878.58,372.24,-5.28 877.39,379.47,-5.28 874.69,389.38,-5.28"/>
        <lane id=":B_6_2" index="2" speed="30.00" length="33.80" shape="878.99,355.45,-5.28 876.62,364.35,-5.28 875.54,371.25,-5.28 874.34,378.48,-5.28 871.65,388.39,-5.28"/>
    </edge>
    <edge id=":B_9" function="internal">
        <lane id=":B_9_0" index="0" speed="11.36" length="12.06" shape="878.99,355.45,-5.28 875.41,362.75,-5.28 872.44,365.32,-5.28"/>
    </edge>
    <edge id=":B_21" function="internal">
        <lane id=":B_21_0" index="0" speed="11.36" length="17.62" shape="872.44,365.32,-5.28 870.35,367.15,-5.28 863.81,368.65,-5.28 855.80,367.26,-5.28"/>
    </edge>
    <edge id=":B_10" function="internal">
        <lane id=":B_10_0" index="0" speed="7.33" length="11.73" shape="858.77,358.13,-5.28 861.27,358.36,-5.28 863.44,357.33,-5.28 865.29,355.04,-5.28 866.81,351.49,-5.28"/>
    </edge>
    <edge id=":B_11" function="internal">
        <lane id=":B_11_0" index="0" speed="30.00" length="33.80" shape="858.77,358.13,-5.28 867.68,360.50,-5.28 874.57,361.58,-5.28 881.80,362.77,-5.28 891.71,365.47,-5.28"/>
        <lane id=":B_11_1" index="1" speed="30.00" length="33.80" shape="857.78,361.17,-5.28 866.69,363.54,-5.28 873.58,364.62,-5.28 880.81,365.82,-5.28 890.72,368.51,-5.28"/>
        <lane id=":B_11_2" index="2" speed="30.00" length="33.80" shape="856.79,364.22,-5.28 865.70,366.58,-5.28 872.59,367.67,-5.28 879.82,368.86,-5.28 889.74,371.56,-5.28"/>
    </edge>
    <edge id=":B_14" function="internal">
        <lane id=":B_14_0" index="0" speed="11.36" length="12.06" shape="856.79,364.22,-5.28 864.09,367.80,-5.28 866.67,370.76,-5.28"/>
    </edge>
    <edge id=":B_22" function="internal">
        <lane id=":B_22_0" index="0" speed="11.36" length="17.62" shape="866.67,370.76,-5.28 868.49,372.86,-5.28 870.00,379.39,-5.28 868.60,387.40,-5.28"/>
    </edge>
    <edge id=":B_15" function="internal">
        <lane id=":B_15_0" index="0" speed="7.33" length="11.73" shape="859.47,384.43,-5.28 859.71,381.93,-5.28 858.68,379.76,-5.28 856.39,377.91,-5.28 852.84,376.39,-5.28"/>
    </edge>
    <edge id=":B_16" function="internal">
        <lane id=":B_16_0" index="0" speed="30.00" length="33.80" shape="859.47,384.43,-5.28 861.84,375.53,-5.28 862.93,368.63,-5.28 864.12,361.40,-5.28 866.81,351.49,-5.28"/>
        <lane id=":B_16_1" index="1" speed="30.00" length="33.80" shape="862.52,385.42,-5.28 864.89,376.51,-5.28 865.97,369.62,-5.28 867.16,362.39,-5.28 869.86,352.48,-5.28"/>
        <lane id=":B_16_2" index="2" speed="30.00" length="33.80" shape="865.56,386.41,-5.28 867.93,377.50,-5.28 869.01,370.61,-5.28 870.21,363.38,-5.28 872.90,353.47,-5.28"/>
    </edge>
    <edge id=":B_19" function="internal">
        <lane id=":B_19_0" index="0" speed="11.36" length="12.06" shape="865.56,386.41,-5.28 869.14,379.11,-5.28 872.10,376.53,-5.28"/>
    </edge>
    <edge id=":B_23" function="internal">
        <lane id=":B_23_0" index="0" speed="11.36" length="17.62" shape="872.10,376.53,-5.28 874.20,374.71,-5.28 880.74,373.20,-5.28 888.75,374.60,-5.28"/>
    </edge>
    <edge id=":BA_0" function="internal">
        <lane id=":BA_0_0" index="0" speed="3.65" length="4.67" shape="783.03,650.78,-5.28 781.90,651.67,-5.28 781.01,651.80,-5.28 780.38,651.17,-5.28 779.99,649.79,-5.28"/>
    </edge>
    <edge id=":BB_0" function="internal">
        <lane id=":BB_0_0" index="0" speed="3.65" length="4.67" shape="1152.12,460.17,-5.28 1153.02,461.31,-5.28 1153.15,462.19,-5.28 1152.52,462.83,-5.28 1151.13,463.22,-5.28"/>
    </edge>
    <edge id=":BC_0" function="internal">
        <lane id=":BC_0_0" index="0" speed="3.65" length="4.67" shape="961.52,91.08,-5.28 962.65,90.19,-5.28 963.54,90.06,-5.28 964.17,90.68,-5.28 964.56,92.07,-5.28"/>
    </edge>
    <edge id=":D_0" function="internal">
        <lane id=":D_0_0" index="0" speed="6.51" length="9.03" shape="494.09,146.85,1.01 492.36,145.07,1.02 490.48,144.27,1.03 488.45,144.45,1.04 486.26,145.61,1.06"/>
    </edge>
    <edge id=":D_1" function="internal">
        <lane id=":D_1_0" index="0" speed="20.00" length="14.40" shape="494.09,146.85,1.01 485.62,135.20,1.06"/>
    </edge>
    <edge id=":D_2" function="internal">
        <lane id=":D_2_0" index="0" speed="6.51" length="9.03" shape="497.91,137.14,1.06 496.14,138.87,1.04 495.34,140.74,1.03 495.52,142.78,1.02 496.67,144.97,1.01"/>
    </edge>
    <edge id=":D_3" function="internal">
        <lane id=":D_3_0" index="0" speed="20.00" length="14.40" shape="497.91,137.14,1.06 486.26,145.61,1.06"/>
    </edge>
    <edge id=":D_4" function="internal">
        <lane id=":D_4_0" index="0" speed="6.51" length="9.03" shape="488.21,133.32,1.06 489.93,135.09,1.06 491.81,135.89,1.06 493.84,135.71,1.06 496.03,134.55,1.06"/>
    </edge>
    <edge id=":D_5" function="internal">
        <lane id=":D_5_0" index="0" speed="20.00" length="14.40" shape="488.21,133.32,1.06 496.67,144.97,1.01"/>
    </edge>
    <edge id=":D_6" function="internal">
        <lane id=":D_6_0" index="0" speed="6.51" length="9.03" shape="484.38,143.02,1.06 486.16,141.30,1.06 486.96,139.42,1.06 486.78,137.38,1.06 485.62,135.20,1.06"/>
    </edge>
    <edge id=":D_7" function="internal">
        <lane id=":D_7_0" index="0" speed="20.00" length="14.40" shape="484.38,143.02,1.06 496.03,134.55,1.06"/>
    </edge>
    <edge id=":DA_0" function="internal">
        <lane id=":DA_0_0" index="0" speed="3.65" length="4.67" shape="630.29,37.01,1.06 631.73,36.95,1.06 632.52,37.37,1.06 632.67,38.25,1.06 632.17,39.60,1.06"/>
    </edge>
    <edge id=":DB_0" function="internal">
        <lane id=":DB_0_0" index="0" speed="3.65" length="4.67" shape="388.08,0.94,1.06 388.02,-0.50,1.06 388.43,-1.29,1.06 389.32,-1.44,1.06 390.67,-0.94,1.06"/>
    </edge>
    <edge id=":DC_0" function="internal">
        <lane id=":DC_0_0" index="0" speed="3.65" length="4.67" shape="352.01,243.15,1.06 350.57,243.21,1.06 349.77,242.80,1.06 349.63,241.91,1.06 350.13,240.56,1.06"/>
    </edge>
    <edge id=":E_0" function="internal">
        <lane id=":E_0_0" index="0" speed="7.33" length="11.73" shape="294.04,394.94,7.22 292.76,392.78,7.22 290.65,391.62,7.22 287.71,391.47,7.22 283.94,392.33,7.22"/>
    </edge>
    <edge id=":E_1" function="internal">
        <lane id=":E_1_0" index="0" speed="30.00" length="33.80" shape="294.04,394.94,7.22 290.72,386.34,7.22 287.55,380.12,7.22 284.26,373.58,7.22 280.62,363.97,7.22"/>
        <lane id=":E_1_1" index="1" speed="30.00" length="33.80" shape="297.09,393.95,7.22 293.77,385.35,7.22 290.59,379.14,7.22 287.31,372.59,7.22 283.66,362.98,7.22"/>
        <lane id=":E_1_2" index="2" speed="30.00" length="33.80" shape="300.13,392.96,7.22 296.81,384.36,7.22 293.64,378.15,7.22 290.35,371.60,7.22 286.70,361.99,7.22"/>
    </edge>
    <edge id=":E_4" function="internal">
        <lane id=":E_4_0" index="0" speed="11.36" length="12.06" shape="300.13,392.96,7.22 298.74,384.95,7.22 299.62,381.12,7.22"/>
    </edge>
    <edge id=":E_20" function="internal">
        <lane id=":E_20_0" index="0" speed="11.36" length="17.62" shape="299.62,381.12,7.22 300.24,378.41,7.22 304.64,373.36,7.22 311.94,369.78,7.22"/>
    </edge>
    <edge id=":E_5" function="internal">
        <lane id=":E_5_0" index="0" speed="7.33" length="11.73" shape="314.91,378.91,7.22 312.75,380.19,7.22 311.60,382.30,7.22 311.45,385.24,7.22 312.30,389.01,7.22"/>
    </edge>
    <edge id=":E_6" function="internal">
        <lane id=":E_6_0" index="0" speed="30.00" length="33.80" shape="314.91,378.91,7.22 306.31,382.23,7.22 300.10,385.40,7.22 293.55,388.69,7.22 283.94,392.33,7.22"/>
        <lane id=":E_6_1" index="1" speed="30.00" length="33.80" shape="313.92,375.86,7.22 305.32,379.18,7.22 299.11,382.36,7.22 292.56,385.64,7.22 282.96,389.29,7.22"/>
        <lane id=":E_6_2" index="2" speed="30.00" length="33.80" shape="312.93,372.82,7.22 304.33,376.14,7.22 298.12,379.31,7.22 291.57,382.60,7.22 281.97,386.24,7.22"/>
    </edge>
    <edge id=":E_9" function="internal">
        <lane id=":E_9_0" index="0" speed="11.36" length="12.06" shape="312.93,372.82,7.22 304.92,374.21,7.22 301.10,373.33,7.22"/>
    </edge>
    <edge id=":E_21" function="internal">
        <lane id=":E_21_0" index="0" speed="11.36" length="17.62" shape="301.10,373.33,7.22 298.39,372.71,7.22 293.33,368.31,7.22 289.75,361.01,7.22"/>
    </edge>
    <edge id=":E_10" function="internal">
        <lane id=":E_10_0" index="0" speed="7.33" length="11.73" shape="298.88,358.04,7.22 300.16,360.20,7.22 302.27,361.35,7.22 305.21,361.50,7.22 308.98,360.65,7.22"/>
    </edge>
    <edge id=":E_11" function="internal">
        <lane id=":E_11_0" index="0" speed="30.00" length="33.80" shape="298.88,358.04,7.22 302.20,366.64,7.22 305.37,372.85,7.22 308.66,379.40,7.22 312.30,389.01,7.22"/>
        <lane id=":E_11_1" index="1" speed="30.00" length="33.80" shape="295.84,359.03,7.22 299.16,367.63,7.22 302.33,373.84,7.22 305.62,380.39,7.22 309.26,389.99,7.22"/>
        <lane id=":E_11_2" index="2" speed="30.00" length="33.80" shape="292.79,360.02,7.22 296.11,368.62,7.22 299.29,374.83,7.22 302.57,381.38,7.22 306.22,390.98,7.22"/>
    </edge>
    <edge id=":E_14" function="internal">
        <lane id=":E_14_0" index="0" speed="11.36" length="12.06" shape="292.79,360.02,7.22 294.19,368.03,7.22 293.30,371.85,7.22"/>
    </edge>
    <edge id=":E_22" function="internal">
        <lane id=":E_22_0" index="0" speed="11.36" length="17.62" shape="293.30,371.85,7.22 292.68,374.56,7.22 288.28,379.62,7.22 280.98,383.20,7.22"/>
    </edge>
    <edge id=":E_15" function="internal">
        <lane id=":E_15_0" index="0" speed="7.33" length="11.73" shape="278.01,374.07,7.22 280.17,372.79,7.22 281.33,370.68,7.22 281.48,367.74,7.22 280.62,363.97,7.22"/>
    </edge>
    <edge id=":E_16" function="internal">
        <lane id=":E_16_0" index="0" speed="30.00" length="33.80" shape="278.01,374.07,7.22 286.61,370.75,7.22 292.83,367.58,7.22 299.37,364.29,7.22 308.98,360.65,7.22"/>
        <lane id=":E_16_1" index="1" speed="30.00" length="33.80" shape="279.00,377.11,7.22 287.60,373.79,7.22 293.81,370.62,7.22 300.36,367.33,7.22 309.97,363.69,7.22"/>
        <lane id=":E_16_2" index="2" speed="30.00" length="33.80" shape="279.99,380.16,7.22 288.59,376.84,7.22 294.80,373.66,7.22 301.35,370.38,7.22 310.96,366.73,7.22"/>
    </edge>
    <edge id=":E_19" function="internal">
        <lane id=":E_19_0" index="0" speed="11.36" length="12.06" shape="279.99,380.16,7.22 288.00,378.76,7.22 291.83,379.65,7.22"/>
    </edge>
    <edge id=":E_23" function="internal">
        <lane id=":E_23_0" index="0" speed="11.36" length="17.62" shape="291.83,379.65,7.22 294.54,380.27,7.22 299.59,384.67,7.22 303.17,391.97,7.22"/>
    </edge>
    <edge id=":EA_0" function="internal">
        <lane id=":EA_0_0" index="0" speed="3.65" length="4.67" shape="198.61,80.52,7.22 199.00,79.13,7.22 199.64,78.51,7.22 200.53,78.64,7.22 201.66,79.53,7.22"/>
    </edge>
    <edge id=":EB_0" function="internal">
        <lane id=":EB_0_0" index="0" speed="3.65" length="4.67" shape="0.49,474.34,7.22 -0.89,473.95,7.22 -1.52,473.31,7.22 -1.39,472.42,7.22 -0.49,471.29,7.22"/>
    </edge>
    <edge id=":EC_0" function="internal">
        <lane id=":EC_0_0" index="0" speed="3.65" length="4.67" shape="394.31,672.46,7.22 393.92,673.84,7.22 393.28,674.47,7.22 392.40,674.34,7.22 391.27,673.44,7.22"/>
    </edge>
    <edge id=":TL_0" function="internal">
        <lane id=":TL_0_0" index="0" speed="6.42" length="10.88" shape="588.12,298.66,-0.11 587.75,295.05,-0.07 586.65,292.74,-0.05 584.80,291.74,-0.03 582.22,292.05"/>
    </edge>
    <edge id=":TL_1" function="internal">
        <lane id=":TL_1_0" index="0" speed="20.00" length="33.56" shape="588.12,298.66,-0.11 587.39,289.93,-0.05 585.54,280.17,0.02 583.15,271.52,0.07 580.76,266.14,0.11"/>
    </edge>
    <edge id=":TL_2" function="internal">
        <lane id=":TL_2_0" index="0" speed="9.61" length="2.67" shape="591.32,298.66,-0.11 591.49,296.00,-0.10"/>
    </edge>
    <edge id=":TL_15" function="internal">
        <lane id=":TL_15_0" index="0" speed="9.61" length="23.28" shape="591.49,296.00,-0.10 591.83,290.67,-0.07 593.77,284.73,-0.05 597.75,281.64,-0.03 604.38,282.20"/>
    </edge>
    <edge id=":TL_3" function="internal">
        <lane id=":TL_3_0" index="0" speed="5.93" length="9.10" shape="600.42,294.38 597.84,293.92,-0.03 596.00,294.49,-0.05 594.89,296.07,-0.08 594.52,298.66,-0.11"/>
    </edge>
    <edge id=":TL_4" function="internal">
        <lane id=":TL_4_0" index="0" speed="16.98" length="21.67" shape="600.42,294.38 595.12,292.42 591.32,291.09 587.52,290.82 582.22,292.05"/>
        <lane id=":TL_4_1" index="1" speed="17.85" length="21.67" shape="601.41,291.33 595.54,289.20 591.32,287.82 587.10,287.60 581.24,289.01"/>
        <lane id=":TL_4_2" index="2" speed="18.68" length="21.67" shape="602.40,288.29 595.96,285.99 591.32,284.54 586.69,284.39 580.25,285.96"/>
        <lane id=":TL_4_3" index="3" speed="19.03" length="21.67" shape="603.39,285.24 596.68,283.34 591.82,282.92 586.96,283.84 580.25,285.96"/>
    </edge>
    <edge id=":TL_8" function="internal">
        <lane id=":TL_8_0" index="0" speed="20.98" length="29.05" shape="603.11,268.86,0.06 600.21,272.62,0.05 595.67,277.27,0.03 589.13,282.00,0.02 580.25,285.96"/>
    </edge>
    <edge id=":TL_9" function="internal">
        <lane id=":TL_9_0" index="0" speed="19.93" length="26.18" shape="583.34,264.26,0.11 586.45,267.25,0.09 591.34,270.20,0.07 597.98,273.14,0.04 606.35,276.11"/>
    </edge>
    <edge id=":TL_10" function="internal">
        <lane id=":TL_10_0" index="0" speed="20.00" length="36.29" shape="583.34,264.26,0.11 586.33,270.64,0.07 590.04,281.10,0.00 593.19,291.74,-0.06 594.52,298.66,-0.11"/>
    </edge>
    <edge id=":TL_11" function="internal">
        <lane id=":TL_11_0" index="0" speed="21.69" length="29.04" shape="576.29,273.79 585.03,271.54 591.35,271.47 597.66,273.14 606.35,276.11"/>
        <lane id=":TL_11_1" index="1" speed="20.98" length="29.04" shape="577.28,276.83 585.44,274.75 591.32,274.73 597.21,276.35 605.37,279.16"/>
        <lane id=":TL_11_2" index="2" speed="20.24" length="29.04" shape="578.27,279.88 585.85,277.96 591.32,278.00 596.79,279.56 604.38,282.20"/>
    </edge>
    <edge id=":TL_14" function="internal">
        <lane id=":TL_14_0" index="0" speed="9.82" length="3.77" shape="579.26,282.92 583.00,282.49,-0.01"/>
    </edge>
    <edge id=":TL_16" function="internal">
        <lane id=":TL_16_0" index="0" speed="9.82" length="23.42" shape="583.00,282.49,-0.01 586.53,282.08,-0.03 591.23,284.81,-0.05 593.77,290.53,-0.07 594.52,298.66,-0.11"/>
    </edge>

    <edge id="A2AA" from="A" to="AA" priority="-1">
        <lane id="A2AA_0" index="0" speed="20.00" length="211.13" shape="582.52,506.49,-1.28 371.40,506.49,-1.28"/>
        <lane id="A2AA_1" index="1" speed="20.00" length="211.13" shape="582.52,503.29,-1.28 371.40,503.29,-1.28"/>
    </edge>
    <edge id="A2AB" from="A" to="AB" priority="-1">
        <lane id="A2AB_0" index="0" speed="20.00" length="211.13" shape="597.72,512.09,-1.28 597.72,723.21,-1.28"/>
        <lane id="A2AB_1" index="1" speed="20.00" length="211.13" shape="594.52,512.09,-1.28 594.52,723.21,-1.28"/>
    </edge>
    <edge id="A2AC" from="A" to="AC" priority="-1">
        <lane id="A2AC_0" index="0" speed="20.00" length="211.13" shape="603.32,496.89,-1.28 814.45,496.89,-1.28"/>
        <lane id="A2AC_1" index="1" speed="20.00" length="211.13" shape="603.32,500.09,-1.28 814.45,500.09,-1.28"/>
    </edge>
    <edge id="A2TL" from="A" to="TL" priority="-1">
        <lane id="A2TL_0" index="0" speed="20.00" length="192.63" shape="588.12,491.29,-1.22 588.12,298.66,-0.11"/>
        <lane id="A2TL_1" index="1" speed="20.00" length="192.63" shape="591.32,491.29,-1.22 591.32,298.66,-0.11"/>
    </edge>
    <edge id="AA2A" from="AA" to="A" priority="-1">
        <lane id="AA2A_0" index="0" speed="20.00" length="211.13" shape="371.40,500.09,-1.28 582.52,500.09,-1.28"/>
    </edge>
    <edge id="AB2A" from="AB" to="A" priority="-1">
        <lane id="AB2A_0" index="0" speed="20.00" length="211.13" shape="591.32,723.21,-1.28 591.32,512.09,-1.28"/>
    </edge>
    <edge id="AC2A" from="AC" to="A" priority="-1">
        <lane id="AC2A_0" index="0" speed="20.00" length="211.13" shape="814.45,503.29,-1.28 603.32,503.29,-1.28"/>
    </edge>
    <edge id="B2BA" from="B" to="BA" priority="-1">
        <lane id="B2BA_0" index="0" speed="30.00" length="276.93" shape="877.74,390.37,-5.28 792.16,653.74,-5.28"/>
        <lane id="B2BA_1" index="1" speed="30.00" length="276.93" shape="874.69,389.38,-5.28 789.12,652.75,-5.28"/>
        <lane id="B2BA_2" index="2" speed="30.00" length="276.93" shape="871.65,388.39,-5.28 786.07,651.76,-5.28"/>
        <lane id="B2BA_3" index="3" speed="30.00" length="276.93" shape="868.60,387.40,-5.28 783.03,650.78,-5.28"/>
    </edge>
    <edge id="B2BB" from="B" to="BB" priority="-1">
        <lane id="B2BB_0" index="0" speed="30.00" length="276.93" shape="891.71,365.47,-5.28 1155.09,451.04,-5.28"/>
        <lane id="B2BB_1" index="1" speed="30.00" length="276.93" shape="890.72,368.51,-5.28 1154.10,454.09,-5.28"/>
        <lane id="B2BB_2" index="2" speed="30.00" length="276.93" shape="889.74,371.56,-5.28 1153.11,457.13,-5.28"/>
        <lane id="B2BB_3" index="3" speed="30.00" length="276.93" shape="888.75,374.60,-5.28 1152.12,460.17,-5.28"/>
    </edge>
    <edge id="B2BC" from="B" to="BC" priority="-1">
        <lane id="B2BC_0" index="0" speed="30.00" length="276.93" shape="866.81,351.49,-5.28 952.39,88.12,-5.28"/>
        <lane id="B2BC_1" index="1" speed="30.00" length="276.93" shape="869.86,352.48,-5.28 955.43,89.11,-5.28"/>
        <lane id="B2BC_2" index="2" speed="30.00" length="276.93" shape="872.90,353.47,-5.28 958.48,90.09,-5.28"/>
        <lane id="B2BC_3" index="3" speed="30.00" length="276.93" shape="875.94,354.46,-5.28 961.52,91.08,-5.28"/>
    </edge>
    <edge id="B2TL" from="B" to="TL" priority="-1">
        <lane id="B2TL_0" index="0" speed="30.00" length="265.46" shape="852.84,376.39,-5.28 600.42,294.38"/>
        <lane id="B2TL_1" index="1" speed="30.00" length="265.46" shape="853.82,373.35,-5.28 601.41,291.33"/>
        <lane id="B2TL_2" index="2" speed="30.00" length="265.46" shape="854.81,370.30,-5.28 602.40,288.29"/>
        <lane id="B2TL_3" index="3" speed="30.00" length="265.46" shape="855.80,367.26,-5.28 603.39,285.24"/>
    </edge>
    <edge id="BA2B" from="BA" to="B" priority="-1">
        <lane id="BA2B_0" index="0" speed="30.00" length="276.93" shape="773.90,647.81,-5.28 859.47,384.43,-5.28"/>
        <lane id="BA2B_1" index="1" speed="30.00" length="276.93" shape="776.94,648.80,-5.28 862.52,385.42,-5.28"/>
        <lane id="BA2B_2" index="2" speed="30.00" length="276.93" shape="779.99,649.79,-5.28 865.56,386.41,-5.28"/>
    </edge>
    <edge id="BB2B" from="BB" to="B" priority="-1">
        <lane id="BB2B_0" index="0" speed="30.00" length="276.93" shape="1149.15,469.30,-5.28 885.78,383.73,-5.28"/>
        <lane id="BB2B_1" index="1" speed="30.00" length="276.93" shape="1150.14,466.26,-5.28 886.77,380.69,-5.28"/>
        <lane id="BB2B_2" index="2" speed="30.00" length="276.93" shape="1151.13,463.22,-5.28 887.76,377.64,-5.28"/>
    </edge>
    <edge id="BC2B" from="BC" to="B" priority="-1">
        <lane id="BC2B_0" index="0" speed="30.00" length="276.93" shape="970.65,94.05,-5.28 885.07,357.42,-5.28"/>
        <lane id="BC2B_1" index="1" speed="30.00" length="276.93" shape="967.61,93.06,-5.28 882.03,356.43,-5.28"/>
        <lane id="BC2B_2" index="2" speed="30.00" length="276.93" shape="964.56,92.07,-5.28 878.99,355.45,-5.28"/>
    </edge>
    <edge id="C2CA" from="C" to="CA" priority="-1">
        <lane id="C2CA_0" index="0" speed="20.00" length="161.43" shape="695.32,147.23,0.61 825.92,242.11,0.61"/>
    </edge>
    <edge id="C2CB" from="C" to="CB" priority="-1">
        <lane id="C2CB_0" index="0" speed="20.00" length="161.43" shape="692.04,141.02,0.61 786.93,10.41,0.61"/>
    </edge>
    <edge id="C2CC" from="C" to="CC" priority="-1">
        <lane id="C2CC_0" index="0" speed="20.00" length="161.43" shape="685.83,144.29,0.61 555.23,49.40,0.61"/>
    </edge>
    <edge id="C2TL" from="C" to="TL" priority="-1">
        <lane id="C2TL_0" index="0" speed="20.00" length="146.30" shape="689.11,150.50,0.59 603.11,268.86,0.06"/>
    </edge>
    <edge id="D2DA" from="D" to="DA" priority="-1">
        <lane id="D2DA_0" index="0" speed="20.00" length="165.95" shape="496.03,134.55,1.06 630.29,37.01,1.06"/>
    </edge>
    <edge id="D2DB" from="D" to="DB" priority="-1">
        <lane id="D2DB_0" index="0" speed="20.00" length="165.95" shape="485.62,135.20,1.06 388.08,0.94,1.06"/>
    </edge>
    <edge id="D2DC" from="D" to="DC" priority="-1">
        <lane id="D2DC_0" index="0" speed="20.00" length="165.95" shape="486.26,145.61,1.06 352.01,243.15,1.06"/>
    </edge>
    <edge id="D2TL" from="D" to="TL" priority="-1">
        <lane id="D2TL_0" index="0" speed="20.00" length="147.45" shape="496.67,144.97,1.01 583.34,264.26,0.11"/>
    </edge>
    <edge id="DA2D" from="DA" to="D" priority="-1">
        <lane id="DA2D_0" index="0" speed="20.00" length="165.95" shape="632.17,39.60,1.06 497.91,137.14,1.06"/>
    </edge>
    <edge id="DB2D" from="DB" to="D" priority="-1">
        <lane id="DB2D_0" index="0" speed="20.00" length="165.95" shape="390.67,-0.94,1.06 488.21,133.32,1.06"/>
    </edge>
    <edge id="DC2D" from="DC" to="D" priority="-1">
        <lane id="DC2D_0" index="0" speed="20.00" length="165.95" shape="350.13,240.56,1.06 484.38,143.02,1.06"/>
    </edge>
    <edge id="E2EA" from="E" to="EA" priority="-1">
        <lane id="E2EA_0" index="0" speed="30.00" length="294.92" shape="280.62,363.97,7.22 189.48,83.49,7.22"/>
        <lane id="E2EA_1" index="1" speed="30.00" length="294.92" shape="283.66,362.98,7.22 192.53,82.50,7.22"/>
        <lane id="E2EA_2" index="2" speed="30.00" length="294.92" shape="286.70,361.99,7.22 195.57,81.51,7.22"/>
        <lane id="E2EA_3" index="3" speed="30.00" length="294.92" shape="289.75,361.01,7.22 198.61,80.52,7.22"/>
    </edge>
    <edge id="E2EB" from="E" to="EB" priority="-1">
        <lane id="E2EB_0" index="0" speed="30.00" length="294.92" shape="283.94,392.33,7.22 3.46,483.47,7.22"/>
        <lane id="E2EB_1" index="1" speed="30.00" length="294.92" shape="282.96,389.29,7.22 2.47,480.42,7.22"/>
        <lane id="E2EB_2" index="2" speed="30.00" length="294.92" shape="281.97,386.24,7.22 1.48,477.38,7.22"/>
        <lane id="E2EB_3" index="3" speed="30.00" length="294.92" shape="280.98,383.20,7.22 0.49,474.34,7.22"/>
    </edge>
    <edge id="E2EC" from="E" to="EC" priority="-1">
        <lane id="E2EC_0" index="0" speed="30.00" length="294.92" shape="312.30,389.01,7.22 403.44,669.49,7.22"/>
        <lane id="E2EC_1" index="1" speed="30.00" length="294.92" shape="309.26,389.99,7.22 400.40,670.48,7.22"/>
        <lane id="E2EC_2" index="2" speed="30.00" length="294.92" shape="306.22,390.98,7.22 397.35,671.47,7.22"/>
        <lane id="E2EC_3" index="3" speed="30.00" length="294.92" shape="303.17,391.97,7.22 394.31,672.46,7.22"/>
    </edge>
    <edge id="E2TL" from="E" to="TL" priority="-1">
        <lane id="E2TL_0" index="0" speed="30.00" length="281.16" shape="308.98,360.65,7.22 576.29,273.79"/>
        <lane id="E2TL_1" index="1" speed="30.00" length="281.16" shape="309.97,363.69,7.22 577.28,276.83"/>
        <lane id="E2TL_2" index="2" speed="30.00" length="281.16" shape="310.96,366.73,7.22 578.27,279.88"/>
        <lane id="E2TL_3" index="3" speed="30.00" length="281.16" shape="311.94,369.78,7.22 579.26,282.92"/>
    </edge>
    <edge id="EA2E" from="EA" to="E" priority="-1">
        <lane id="EA2E_0" index="0" speed="30.00" length="294.92" shape="207.74,77.55,7.22 298.88,358.04,7.22"/>
        <lane id="EA2E_1" index="1" speed="30.00" length="294.92" shape="204.70,78.54,7.22 295.84,359.03,7.22"/>
        <lane id="EA2E_2" index="2" speed="30.00" length="294.92" shape="201.66,79.53,7.22 292.79,360.02,7.22"/>
    </edge>
    <edge id="EB2E" from="EB" to="E" priority="-1">
        <lane id="EB2E_0" index="0" speed="30.00" length="294.92" shape="-2.47,465.21,7.22 278.01,374.07,7.22"/>
        <lane id="EB2E_1" index="1" speed="30.00" length="294.92" shape="-1.48,468.25,7.22 279.00,377.11,7.22"/>
        <lane id="EB2E_2" index="2" speed="30.00" length="294.92" shape="-0.49,471.29,7.22 279.99,380.16,7.22"/>
    </edge>
    <edge id="EC2E" from="EC" to="E" priority="-1">
        <lane id="EC2E_0" index="0" speed="30.00" length="294.92" shape="385.18,675.42,7.22 294.04,394.94,7.22"/>
        <lane id="EC2E_1" index="1" speed="30.00" length="294.92" shape="388.22,674.43,7.22 297.09,393.95,7.22"/>
        <lane id="EC2E_2" index="2" speed="30.00" length="294.92" shape="391.27,673.44,7.22 300.13,392.96,7.22"/>
    </edge>
    <edge id="TL2A" from="TL" to="A" priority="-1">
        <lane id="TL2A_0" index="0" speed="20.00" length="192.63" shape="594.52,298.66,-0.11 594.52,491.29,-1.22"/>
    </edge>
    <edge id="TL2B" from="TL" to="B" priority="-1">
        <lane id="TL2B_0" index="0" speed="30.00" length="265.46" shape="606.35,276.11 858.77,358.13,-5.28"/>
        <lane id="TL2B_1" index="1" speed="30.00" length="265.46" shape="605.37,279.16 857.78,361.17,-5.28"/>
        <lane id="TL2B_2" index="2" speed="30.00" length="265.46" shape="604.38,282.20 856.79,364.22,-5.28"/>
    </edge>
    <edge id="TL2D" from="TL" to="D" priority="-1">
        <lane id="TL2D_0" index="0" speed="20.00" length="147.45" shape="580.76,266.14,0.11 494.09,146.85,1.01"/>
    </edge>
    <edge id="TL2E" from="TL" to="E" priority="-1">
        <lane id="TL2E_0" index="0" speed="30.00" length="281.16" shape="582.22,292.05 314.91,378.91,7.22"/>
        <lane id="TL2E_1" index="1" speed="30.00" length="281.16" shape="581.24,289.01 313.92,375.86,7.22"/>
        <lane id="TL2E_2" index="2" speed="30.00" length="281.16" shape="580.25,285.96 312.93,372.82,7.22"/>
    </edge>

    <tlLogic id="A" type="static" programID="0" offset="0">
        <phase duration="40" state="GGrrGGrr"/>
        <phase duration="5"  state="yyrryyrr"/>
        <phase duration="40" state="rrGGrrGG"/>
        <phase duration="5"  state="rryyrryy"/>
    </tlLogic>
    <tlLogic id="AA" type="static" programID="0" offset="0">
        <phase duration="80" state="G"/>
        <phase duration="5"  state="y"/>
        <phase duration="5"  state="r"/>
    </tlLogic>
    <tlLogic id="AB" type="static" programID="0" offset="0">
        <phase duration="80" state="G"/>
        <phase duration="5"  state="y"/>
        <phase duration="5"  state="r"/>
    </tlLogic>
    <tlLogic id="AC" type="static" programID="0" offset="0">
        <phase duration="80" state="G"/>
        <phase duration="5"  state="y"/>
        <phase duration="5"  state="r"/>
    </tlLogic>
    <tlLogic id="B" type="static" programID="0" offset="0">
        <phase duration="39" state="GGGGgrrrrrGGGGgrrrrr"/>
        <phase duration="6"  state="yyyyyrrrrryyyyyrrrrr"/>
        <phase duration="39" state="rrrrrGGGGgrrrrrGGGGg"/>
        <phase duration="6"  state="rrrrryyyyyrrrrryyyyy"/>
    </tlLogic>
    <tlLogic id="BA" type="static" programID="0" offset="0">
        <phase duration="79" state="G"/>
        <phase duration="6"  state="y"/>
        <phase duration="5"  state="r"/>
    </tlLogic>
    <tlLogic id="BB" type="static" programID="0" offset="0">
        <phase duration="79" state="G"/>
        <phase duration="6"  state="y"/>
        <phase duration="5"  state="r"/>
    </tlLogic>
    <tlLogic id="BC" type="static" programID="0" offset="0">
        <phase duration="79" state="G"/>
        <phase duration="6"  state="y"/>
        <phase duration="5"  state="r"/>
    </tlLogic>
    <tlLogic id="D" type="static" programID="0" offset="0">
        <phase duration="40" state="GGrrGGrr"/>
        <phase duration="5"  state="yyrryyrr"/>
        <phase duration="40" state="rrGGrrGG"/>
        <phase duration="5"  state="rryyrryy"/>
    </tlLogic>
    <tlLogic id="DA" type="static" programID="0" offset="0">
        <phase duration="80" state="G"/>
        <phase duration="5"  state="y"/>
        <phase duration="5"  state="r"/>
    </tlLogic>
    <tlLogic id="DB" type="static" programID="0" offset="0">
        <phase duration="80" state="G"/>
        <phase duration="5"  state="y"/>
        <phase duration="5"  state="r"/>
    </tlLogic>
    <tlLogic id="DC" type="static" programID="0" offset="0">
        <phase duration="80" state="G"/>
        <phase duration="5"  state="y"/>
        <phase duration="5"  state="r"/>
    </tlLogic>
    <tlLogic id="E" type="static" programID="0" offset="0">
        <phase duration="39" state="GGGGgrrrrrGGGGgrrrrr"/>
        <phase duration="6"  state="yyyyyrrrrryyyyyrrrrr"/>
        <phase duration="39" state="rrrrrGGGGgrrrrrGGGGg"/>
        <phase duration="6"  state="rrrrryyyyyrrrrryyyyy"/>
    </tlLogic>
    <tlLogic id="EA" type="static" programID="0" offset="0">
        <phase duration="79" state="G"/>
        <phase duration="6"  state="y"/>
        <phase duration="5"  state="r"/>
    </tlLogic>
    <tlLogic id="EB" type="static" programID="0" offset="0">
        <phase duration="79" state="G"/>
        <phase duration="6"  state="y"/>
        <phase duration="5"  state="r"/>
    </tlLogic>
    <tlLogic id="EC" type="static" programID="0" offset="0">
        <phase duration="79" state="G"/>
        <phase duration="6"  state="y"/>
        <phase duration="5"  state="r"/>
    </tlLogic>
    <tlLogic id="TL" type="static" programID="0" offset="0">
        <phase duration="16" state="srrGGGgGrrrGGGr"/>
        <phase duration="6"  state="srryyyyyrrryyyr"/>
        <phase duration="6"  state="srrrrrrrrrrGGGG"/>
        <phase duration="6"  state="srrrrrrrrrryyyy"/>
        <phase duration="16" state="GGrrrrrrrGGrrrr"/>
        <phase duration="6"  state="yyrrrrrrryyrrrr"/>
        <phase duration="6"  state="GGGsrrrrrrrrrrr"/>
        <phase duration="6"  state="yyysrrrrrrrrrrr"/>
        <phase duration="16" state="srGGrrrrGrrrrrr"/>
        <phase duration="6"  state="sryyrrrryrrrrrr"/>
    </tlLogic>

    <junction id="A" type="traffic_light" x="592.92" y="501.69" z="-1.28" incLanes="AB2A_0 AC2A_0 TL2A_0 AA2A_0" intLanes=":A_0_0 :A_1_0 :A_2_0 :A_3_0 :A_4_0 :A_5_0 :A_6_0 :A_7_0" shape="589.72,512.09,-1.28 599.32,512.09,-1.28 599.43,509.89,-1.28 599.77,508.09,-1.28 600.32,506.69,-1.28 601.10,505.69,-1.28 602.10,505.09,-1.28 603.32,504.89,-1.28 603.32,495.29,-1.28 601.12,495.18,-1.28 599.32,494.84,-1.28 597.92,494.29,-1.28 596.92,493.51,-1.28 596.32,492.51,-1.28 596.12,491.29,-1.28 586.52,491.29,-1.28 586.41,493.49,-1.28 586.08,495.29,-1.28 585.52,496.69,-1.28 584.75,497.69,-1.28 583.75,498.29,-1.28 582.52,498.49,-1.28 582.52,508.09,-1.28 584.72,508.20,-1.28 586.52,508.53,-1.28 587.92,509.09,-1.28 588.92,509.87,-1.28 589.52,510.87,-1.28">
        <request index="0" response="00000000" foes="00001000" cont="0"/>
        <request index="1" response="00000000" foes="11001000" cont="0"/>
        <request index="2" response="00100000" foes="00100000" cont="0"/>
        <request index="3" response="00100011" foes="00100011" cont="0"/>
        <request index="4" response="00000000" foes="10000000" cont="0"/>
        <request index="5" response="00000000" foes="10001100" cont="0"/>
        <request index="6" response="00000010" foes="00000010" cont="0"/>
        <request index="7" response="00110010" foes="00110010" cont="0"/>
    </junction>
    <junction id="AA" type="traffic_light" x="371.40" y="501.69" z="-1.28" incLanes="A2AA_0 A2AA_1" intLanes=":AA_0_0" shape="371.40,501.69,-1.28 371.40,508.09,-1.28 371.40,501.69,-1.28">
        <request index="0" response="0" foes="0" cont="0"/>
    </junction>
    <junction id="AB" type="traffic_light" x="592.92" y="723.21" z="-1.28" incLanes="A2AB_0 A2AB_1" intLanes=":AB_0_0" shape="592.92,723.21,-1.28 599.32,723.21,-1.28 592.92,723.21,-1.28">
        <request index="0" response="0" foes="0" cont="0"/>
    </junction>
    <junction id="AC" type="traffic_light" x="814.45" y="501.69" z="-1.28" incLanes="A2AC_0 A2AC_1" intLanes=":AC_0_0" shape="814.45,501.69,-1.28 814.45,495.29,-1.28 814.45,501.69,-1.28">
        <request index="0" response="0" foes="0" cont="0"/>
    </junction>
    <junction id="B" type="traffic_light" x="872.27" y="370.93" z="-5.28" incLanes="BB2B_0 BB2B_1 BB2B_2 BC2B_0 BC2B_1 BC2B_2 TL2B_0 TL2B_1 TL2B_2 BA2B_0 BA2B_1 BA2B_2" intLanes=":B_0_0 :B_1_0 :B_1_1 :B_1_2 :B_20_0 :B_5_0 :B_6_0 :B_6_1 :B_6_2 :B_21_0 :B_10_0 :B_11_0 :B_11_1 :B_11_2 :B_22_0 :B_15_0 :B_16_0 :B_16_1 :B_16_2 :B_23_0" shape="885.29,385.25,-5.28 892.21,363.95,-5.28 890.15,363.16,-5.28 888.54,362.29,-5.28 887.38,361.33,-5.28 886.67,360.28,-5.28 886.41,359.14,-5.28 886.60,357.92,-5.28 865.29,351.00,-5.28 864.51,353.05,-5.28 863.63,354.66,-5.28 862.67,355.82,-5.28 861.62,356.53,-5.28 860.49,356.79,-5.28 859.26,356.61,-5.28 852.34,377.91,-5.28 854.40,378.70,-5.28 856.01,379.57,-5.28 857.17,380.53,-5.28 857.88,381.58,-5.28 858.14,382.72,-5.28 857.95,383.94,-5.28 879.26,390.86,-5.28 880.04,388.80,-5.28 880.92,387.20,-5.28 881.88,386.04,-5.28 882.93,385.32,-5.28 884.06,385.06,-5.28">
        <request index="0"  response="00000000000000000000" foes="00000000000111000000" cont="0"/>
        <request index="1"  response="10000000000000000000" foes="11111100000111000000" cont="0"/>
        <request index="2"  response="10000000000000000000" foes="11111100000111000000" cont="0"/>
        <request index="3"  response="10000000000000000000" foes="11111100000111000000" cont="0"/>
        <request index="4"  response="10000011101000000000" foes="10000011101111000000" cont="1"/>
        <request index="5"  response="00000011100000000000" foes="00000011100000000000" cont="0"/>
        <request index="6"  response="00000011100000011111" foes="10000011100000011111" cont="0"/>
        <request index="7"  response="00000011100000011111" foes="10000011100000011111" cont="0"/>
        <request index="8"  response="00000011100000011111" foes="10000011100000011111" cont="0"/>
        <request index="9"  response="01110111100000010000" foes="01110111100000010000" cont="1"/>
        <request index="10" response="00000000000000000000" foes="01110000000000000000" cont="0"/>
        <request index="11" response="00000000001000000000" foes="01110000001111110000" cont="0"/>
        <request index="12" response="00000000001000000000" foes="01110000001111110000" cont="0"/>
        <request index="13" response="00000000001000000000" foes="01110000001111110000" cont="0"/>
        <request index="14" response="10000000001000001110" foes="11110000001000001110" cont="1"/>
        <request index="15" response="00000000000000001110" foes="00000000000000001110" cont="0"/>
        <request index="16" response="00000111110000001110" foes="00000111111000001110" cont="0"/>
        <request index="17" response="00000111110000001110" foes="00000111111000001110" cont="0"/>
        <request index="18" response="00000111110000001110" foes="00000111111000001110" cont="0"/>
        <request index="19" response="00000100000111011110" foes="00000100000111011110" cont="1"/>
    </junction>
    <junction id="BA" type="traffic_light" x="781.51" y="650.28" z="-5.28" incLanes="B2BA_0 B2BA_1 B2BA_2 B2BA_3" intLanes=":BA_0_0" shape="781.51,650.28,-5.28 793.68,654.24,-5.28 781.51,650.28,-5.28">
        <request index="0" response="0" foes="0" cont="0"/>
    </junction>
    <junction id="BB" type="traffic_light" x="1151.63" y="461.70" z="-5.28" incLanes="B2BB_0 B2BB_1 B2BB_2 B2BB_3" intLanes=":BB_0_0" shape="1151.63,461.70,-5.28 1155.58,449.52,-5.28 1151.63,461.70,-5.28">
        <request index="0" response="0" foes="0" cont="0"/>
    </junction>
    <junction id="BC" type="traffic_light" x="963.04" y="91.58" z="-5.28" incLanes="B2BC_0 B2BC_1 B2BC_2 B2BC_3" intLanes=":BC_0_0" shape="963.04,91.58,-5.28 950.87,87.62,-5.28 963.04,91.58,-5.28">
        <request index="0" response="0" foes="0" cont="0"/>
    </junction>
    <junction id="C" type="dead_end" x="690.57" y="145.76" z="0.61" incLanes="" intLanes="" shape="694.38,148.52,0.61 696.26,145.93,0.61 694.24,144.26,0.61 693.63,143.56,0.61 693.27,142.94,0.61 693.17,142.40,0.61 693.34,141.96,0.61 690.75,140.07,0.61 689.08,142.09,0.61 688.37,142.71,0.61 687.75,143.06,0.61 687.22,143.16,0.61 686.77,143.00,0.61 684.89,145.58,0.61 686.90,147.25,0.61 687.52,147.96,0.61 687.88,148.58,0.61 687.97,149.11,0.61 687.81,149.56,0.61 690.40,151.44,0.61 692.07,149.43,0.61 692.77,148.81,0.61 693.39,148.45,0.61 693.93,148.36,0.61"/>
    <junction id="CA" type="dead_end" x="824.98" y="243.41" z="0.61" incLanes="C2CA_0" intLanes="" shape="826.86,240.82,0.61 824.98,243.41,0.61"/>
    <junction id="CB" type="dead_end" x="788.22" y="11.35" z="0.61" incLanes="C2CB_0" intLanes="" shape="785.63,9.47,0.61 788.22,11.35,0.61"/>
    <junction id="CC" type="dead_end" x="556.17" y="48.11" z="0.61" incLanes="C2CC_0" intLanes="" shape="554.29,50.70,0.61 556.17,48.11,0.61"/>
    <junction id="D" type="traffic_light" x="491.15" y="140.08" z="1.06" incLanes="TL2D_0 DA2D_0 DB2D_0 DC2D_0" intLanes=":D_0_0 :D_1_0 :D_2_0 :D_3_0 :D_4_0 :D_5_0 :D_6_0 :D_7_0" shape="492.79,147.79,1.06 497.97,144.03,1.06 497.02,141.97,1.06 497.01,141.01,1.06 497.32,140.10,1.06 497.93,139.25,1.06 498.85,138.44,1.06 495.09,133.26,1.06 493.03,134.21,1.06 492.08,134.21,1.06 491.17,133.91,1.06 490.31,133.30,1.06 489.50,132.38,1.06 484.33,136.14,1.06 485.27,138.20,1.06 485.28,139.15,1.06 484.98,140.06,1.06 484.37,140.92,1.06 483.44,141.72,1.06 487.20,146.90,1.06 489.26,145.96,1.06 490.22,145.95,1.06 491.13,146.25,1.06 491.98,146.86,1.06">
        <request index="0" response="00000000" foes="00001000" cont="0"/>
        <request index="1" response="00000000" foes="11001000" cont="0"/>
        <request index="2" response="00100000" foes="00100000" cont="0"/>
        <request index="3" response="00100011" foes="00100011" cont="0"/>
        <request index="4" response="00000000" foes="10000000" cont="0"/>
        <request index="5" response="00000000" foes="10001100" cont="0"/>
        <request index="6" response="00000010" foes="00000010" cont="0"/>
        <request index="7" response="00110010" foes="00110010" cont="0"/>
    </junction>
    <junction id="DA" type="traffic_light" x="631.23" y="38.31" z="1.06" incLanes="D2DA_0" intLanes=":DA_0_0" shape="631.23,38.31,1.06 629.35,35.72,1.06 631.23,38.31,1.06">
        <request index="0" response="0" foes="0" cont="0"/>
    </junction>
    <junction id="DB" type="traffic_light" x="389.37" y="0.00" z="1.06" incLanes="D2DB_0" intLanes=":DB_0_0" shape="389.37,0.00,1.06 386.78,1.88,1.06 389.37,0.00,1.06">
        <request index="0" response="0" foes="0" cont="0"/>
    </junction>
    <junction id="DC" type="traffic_light" x="351.07" y="241.86" z="1.06" incLanes="D2DC_0" intLanes=":DC_0_0" shape="351.07,241.86,1.06 352.95,244.44,1.06 351.07,241.86,1.06">
        <request index="0" response="0" foes="0" cont="0"/>
    </junction>
    <junction id="E" type="traffic_light" x="296.46" y="376.49" z="7.22" incLanes="EC2E_0 EC2E_1 EC2E_2 TL2E_0 TL2E_1 TL2E_2 EA2E_0 EA2E_1 EA2E_2 EB2E_0 EB2E_1 EB2E_2" intLanes=":E_0_0 :E_1_0 :E_1_1 :E_1_2 :E_20_0 :E_5_0 :E_6_0 :E_6_1 :E_6_2 :E_21_0 :E_10_0 :E_11_0 :E_11_1 :E_11_2 :E_22_0 :E_15_0 :E_16_0 :E_16_1 :E_16_2 :E_23_0" shape="292.52,395.43,7.22 313.83,388.51,7.22 313.25,386.38,7.22 313.01,384.57,7.22 313.11,383.07,7.22 313.54,381.87,7.22 314.31,380.99,7.22 315.41,380.43,7.22 308.48,359.12,7.22 306.36,359.70,7.22 304.54,359.94,7.22 303.04,359.84,7.22 301.85,359.41,7.22 300.97,358.64,7.22 300.40,357.54,7.22 279.10,364.47,7.22 279.67,366.59,7.22 279.91,368.41,7.22 279.81,369.91,7.22 279.38,371.10,7.22 278.62,371.98,7.22 277.52,372.55,7.22 284.44,393.85,7.22 286.57,393.28,7.22 288.38,393.04,7.22 289.88,393.14,7.22 291.08,393.57,7.22 291.95,394.33,7.22">
        <request index="0"  response="00000000000000000000" foes="00000000000111000000" cont="0"/>
        <request index="1"  response="10000000000000000000" foes="11111100000111000000" cont="0"/>
        <request index="2"  response="10000000000000000000" foes="11111100000111000000" cont="0"/>
        <request index="3"  response="10000000000000000000" foes="11111100000111000000" cont="0"/>
        <request index="4"  response="10000011101000000000" foes="10000011101111000000" cont="1"/>
        <request index="5"  response="00000011100000000000" foes="00000011100000000000" cont="0"/>
        <request index="6"  response="00000011100000011111" foes="10000011100000011111" cont="0"/>
        <request index="7"  response="00000011100000011111" foes="10000011100000011111" cont="0"/>
        <request index="8"  response="00000011100000011111" foes="10000011100000011111" cont="0"/>
        <request index="9"  response="01110111100000010000" foes="01110111100000010000" cont="1"/>
        <request index="10" response="00000000000000000000" foes="01110000000000000000" cont="0"/>
        <request index="11" response="00000000001000000000" foes="01110000001111110000" cont="0"/>
        <request index="12" response="00000000001000000000" foes="01110000001111110000" cont="0"/>
        <request index="13" response="00000000001000000000" foes="01110000001111110000" cont="0"/>
        <request index="14" response="10000000001000001110" foes="11110000001000001110" cont="1"/>
        <request index="15" response="00000000000000001110" foes="00000000000000001110" cont="0"/>
        <request index="16" response="00000111110000001110" foes="00000111111000001110" cont="0"/>
        <request index="17" response="00000111110000001110" foes="00000111111000001110" cont="0"/>
        <request index="18" response="00000111110000001110" foes="00000111111000001110" cont="0"/>
        <request index="19" response="00000100000111011110" foes="00000100000111011110" cont="1"/>
    </junction>
    <junction id="EA" type="traffic_light" x="200.14" y="80.03" z="7.22" incLanes="E2EA_0 E2EA_1 E2EA_2 E2EA_3" intLanes=":EA_0_0" shape="200.14,80.03,7.22 187.96,83.98,7.22 200.14,80.03,7.22">
        <request index="0" response="0" foes="0" cont="0"/>
    </junction>
    <junction id="EB" type="traffic_light" x="0.00" y="472.81" z="7.22" incLanes="E2EB_0 E2EB_1 E2EB_2 E2EB_3" intLanes=":EB_0_0" shape="0.00,472.81,7.22 3.96,484.99,7.22 0.00,472.81,7.22">
        <request index="0" response="0" foes="0" cont="0"/>
    </junction>
    <junction id="EC" type="traffic_light" x="392.79" y="672.95" z="7.22" incLanes="E2EC_0 E2EC_1 E2EC_2 E2EC_3" intLanes=":EC_0_0" shape="392.79,672.95,7.22 404.96,668.99,7.22 392.79,672.95,7.22">
        <request index="0" response="0" foes="0" cont="0"/>
    </junction>
    <junction id="TL" type="traffic_light_right_on_red" x="592.92" y="280.16" incLanes="A2TL_0 A2TL_1 B2TL_0 B2TL_1 B2TL_2 B2TL_3 C2TL_0 D2TL_0 E2TL_0 E2TL_1 E2TL_2 E2TL_3" intLanes=":TL_0_0 :TL_1_0 :TL_15_0 :TL_3_0 :TL_4_0 :TL_4_1 :TL_4_2 :TL_4_3 :TL_8_0 :TL_9_0 :TL_10_0 :TL_11_0 :TL_11_1 :TL_11_2 :TL_16_0" shape="586.52,298.66 596.12,298.66 596.55,296.58 597.07,295.97 597.81,295.65 598.76,295.63 599.93,295.90 606.85,274.59 604.45,273.37 603.84,272.62 603.63,271.77 603.82,270.83 604.41,269.80 601.82,267.92 599.42,270.44 596.83,271.64 594.06,271.53 591.11,270.10 587.97,267.37 584.64,263.32 579.46,267.08 580.10,269.09 579.72,269.99 578.88,270.82 577.57,271.58 575.80,272.27 582.72,293.57 584.83,293.59 585.57,294.23 586.10,295.28 586.42,296.76">
        <request index="0"  response="000000111110000" foes="000000011110000" cont="0"/>
        <request index="1"  response="111100011110000" foes="111100111110000" cont="0"/>
        <request index="2"  response="111110011110000" foes="111110011110000" cont="1"/>
        <request index="3"  response="000000000000000" foes="100010000000000" cont="0"/>
        <request index="4"  response="000000000000100" foes="100010100000111" cont="0"/>
        <request index="5"  response="000000000000100" foes="100010100000111" cont="0"/>
        <request index="6"  response="000000010000100" foes="100010110000111" cont="0"/>
        <request index="7"  response="000000000000100" foes="100010101000111" cont="0"/>
        <request index="8"  response="111100011110010" foes="111111011110010" cont="0"/>
        <request index="9"  response="011100100000000" foes="011100100000000" cont="0"/>
        <request index="10" response="111100111111000" foes="111100111111100" cont="0"/>
        <request index="11" response="000000000000100" foes="000011100000110" cont="0"/>
        <request index="12" response="000000000000100" foes="000011100000110" cont="0"/>
        <request index="13" response="000000000000100" foes="000011100000110" cont="0"/>
        <request index="14" response="000000011111100" foes="000010111111110" cont="1"/>
    </junction>

    <junction id=":B_20_0" type="internal" x="877.88" y="371.10" z="-5.28" incLanes=":B_4_0 TL2B_0 TL2B_1 TL2B_2" intLanes=":B_6_0 :B_6_1 :B_6_2 :B_9_0 :B_10_0 :B_11_0 :B_11_1 :B_11_2 :B_16_0 :B_16_1 :B_16_2 :B_19_0"/>
    <junction id=":B_21_0" type="internal" x="872.44" y="365.32" z="-5.28" incLanes=":B_9_0 BA2B_0 BA2B_1 BA2B_2" intLanes=":B_1_0 :B_1_1 :B_1_2 :B_4_0 :B_11_0 :B_11_1 :B_11_2 :B_14_0 :B_15_0 :B_16_0 :B_16_1 :B_16_2"/>
    <junction id=":B_22_0" type="internal" x="866.67" y="370.76" z="-5.28" incLanes=":B_14_0 BB2B_0 BB2B_1 BB2B_2" intLanes=":B_0_0 :B_1_0 :B_1_1 :B_1_2 :B_6_0 :B_6_1 :B_6_2 :B_9_0 :B_16_0 :B_16_1 :B_16_2 :B_19_0"/>
    <junction id=":B_23_0" type="internal" x="872.10" y="376.53" z="-5.28" incLanes=":B_19_0 BC2B_0 BC2B_1 BC2B_2" intLanes=":B_1_0 :B_1_1 :B_1_2 :B_4_0 :B_5_0 :B_6_0 :B_6_1 :B_6_2 :B_11_0 :B_11_1 :B_11_2 :B_14_0"/>
    <junction id=":E_20_0" type="internal" x="299.62" y="381.12" z="7.22" incLanes=":E_4_0 EA2E_0 EA2E_1 EA2E_2" intLanes=":E_6_0 :E_6_1 :E_6_2 :E_9_0 :E_10_0 :E_11_0 :E_11_1 :E_11_2 :E_16_0 :E_16_1 :E_16_2 :E_19_0"/>
    <junction id=":E_21_0" type="internal" x="301.10" y="373.33" z="7.22" incLanes=":E_9_0 EB2E_0 EB2E_1 EB2E_2" intLanes=":E_1_0 :E_1_1 :E_1_2 :E_4_0 :E_11_0 :E_11_1 :E_11_2 :E_14_0 :E_15_0 :E_16_0 :E_16_1 :E_16_2"/>
    <junction id=":E_22_0" type="internal" x="293.30" y="371.85" z="7.22" incLanes=":E_14_0 EC2E_0 EC2E_1 EC2E_2" intLanes=":E_0_0 :E_1_0 :E_1_1 :E_1_2 :E_6_0 :E_6_1 :E_6_2 :E_9_0 :E_16_0 :E_16_1 :E_16_2 :E_19_0"/>
    <junction id=":E_23_0" type="internal" x="291.83" y="379.65" z="7.22" incLanes=":E_19_0 TL2E_0 TL2E_1 TL2E_2" intLanes=":E_1_0 :E_1_1 :E_1_2 :E_4_0 :E_5_0 :E_6_0 :E_6_1 :E_6_2 :E_11_0 :E_11_1 :E_11_2 :E_14_0"/>
    <junction id=":TL_15_0" type="internal" x="591.49" y="296.00" z="-0.10" incLanes=":TL_2_0 D2TL_0" intLanes=":TL_4_0 :TL_4_1 :TL_4_2 :TL_4_3 :TL_9_0 :TL_10_0 :TL_11_0 :TL_11_1 :TL_11_2 :TL_14_0"/>
    <junction id=":TL_16_0" type="internal" x="583.00" y="282.49" z="-0.01" incLanes=":TL_14_0 B2TL_0 B2TL_1 B2TL_2 B2TL_3" intLanes=":TL_1_0 :TL_2_0 :TL_3_0 :TL_4_0 :TL_4_1 :TL_4_2 :TL_4_3 :TL_8_0 :TL_10_0"/>

    <connection from="A2AA" to="AA2A" fromLane="1" toLane="0" via=":AA_0_0" tl="AA" linkIndex="0" dir="t" state="O"/>
    <connection from="A2AB" to="AB2A" fromLane="1" toLane="0" via=":AB_0_0" tl="AB" linkIndex="0" dir="t" state="O"/>
    <connection from="A2AC" to="AC2A" fromLane="1" toLane="0" via=":AC_0_0" tl="AC" linkIndex="0" dir="t" state="O"/>
    <connection from="A2TL" to="TL2E" fromLane="0" toLane="0" via=":TL_0_0" tl="TL" linkIndex="0" dir="r" state="o"/>
    <connection from="A2TL" to="TL2D" fromLane="0" toLane="0" via=":TL_1_0" tl="TL" linkIndex="1" dir="s" state="o"/>
    <connection from="A2TL" to="TL2B" fromLane="1" toLane="2" via=":TL_2_0" tl="TL" linkIndex="2" dir="l" state="o"/>
    <connection from="AA2A" to="A2TL" fromLane="0" toLane="0" via=":A_6_0" tl="A" linkIndex="6" dir="r" state="o"/>
    <connection from="AA2A" to="A2AC" fromLane="0" toLane="0" via=":A_7_0" tl="A" linkIndex="7" dir="s" state="o"/>
    <connection from="AB2A" to="A2AA" fromLane="0" toLane="0" via=":A_0_0" tl="A" linkIndex="0" dir="r" state="O"/>
    <connection from="AB2A" to="A2TL" fromLane="0" toLane="0" via=":A_1_0" tl="A" linkIndex="1" dir="s" state="O"/>
    <connection from="AC2A" to="A2AB" fromLane="0" toLane="0" via=":A_2_0" tl="A" linkIndex="2" dir="r" state="o"/>
    <connection from="AC2A" to="A2AA" fromLane="0" toLane="0" via=":A_3_0" tl="A" linkIndex="3" dir="s" state="o"/>
    <connection from="B2BA" to="BA2B" fromLane="3" toLane="2" via=":BA_0_0" tl="BA" linkIndex="0" dir="t" state="O"/>
    <connection from="B2BB" to="BB2B" fromLane="3" toLane="2" via=":BB_0_0" tl="BB" linkIndex="0" dir="t" state="O"/>
    <connection from="B2BC" to="BC2B" fromLane="3" toLane="2" via=":BC_0_0" tl="BC" linkIndex="0" dir="t" state="O"/>
    <connection from="B2TL" to="TL2A" fromLane="0" toLane="0" via=":TL_3_0" tl="TL" linkIndex="3" dir="r" state="O"/>
    <connection from="B2TL" to="TL2E" fromLane="0" toLane="0" via=":TL_4_0" tl="TL" linkIndex="4" dir="s" state="O"/>
    <connection from="B2TL" to="TL2E" fromLane="1" toLane="1" via=":TL_4_1" tl="TL" linkIndex="5" dir="s" state="O"/>
    <connection from="B2TL" to="TL2E" fromLane="2" toLane="2" via=":TL_4_2" tl="TL" linkIndex="6" dir="s" state="o"/>
    <connection from="B2TL" to="TL2E" fromLane="3" toLane="2" via=":TL_4_3" tl="TL" linkIndex="7" dir="s" state="O"/>
    <connection from="BA2B" to="B2TL" fromLane="0" toLane="0" via=":B_15_0" tl="B" linkIndex="15" dir="r" state="o"/>
    <connection from="BA2B" to="B2BC" fromLane="0" toLane="0" via=":B_16_0" tl="B" linkIndex="16" dir="s" state="o"/>
    <connection from="BA2B" to="B2BC" fromLane="1" toLane="1" via=":B_16_1" tl="B" linkIndex="17" dir="s" state="o"/>
    <connection from="BA2B" to="B2BC" fromLane="2" toLane="2" via=":B_16_2" tl="B" linkIndex="18" dir="s" state="o"/>
    <connection from="BA2B" to="B2BB" fromLane="2" toLane="3" via=":B_19_0" tl="B" linkIndex="19" dir="l" state="o"/>
    <connection from="BB2B" to="B2BA" fromLane="0" toLane="0" via=":B_0_0" tl="B" linkIndex="0" dir="r" state="O"/>
    <connection from="BB2B" to="B2TL" fromLane="0" toLane="0" via=":B_1_0" tl="B" linkIndex="1" dir="s" state="O"/>
    <connection from="BB2B" to="B2TL" fromLane="1" toLane="1" via=":B_1_1" tl="B" linkIndex="2" dir="s" state="O"/>
    <connection from="BB2B" to="B2TL" fromLane="2" toLane="2" via=":B_1_2" tl="B" linkIndex="3" dir="s" state="O"/>
    <connection from="BB2B" to="B2BC" fromLane="2" toLane="3" via=":B_4_0" tl="B" linkIndex="4" dir="l" state="o"/>
    <connection from="BC2B" to="B2BB" fromLane="0" toLane="0" via=":B_5_0" tl="B" linkIndex="5" dir="r" state="o"/>
    <connection from="BC2B" to="B2BA" fromLane="0" toLane="0" via=":B_6_0" tl="B" linkIndex="6" dir="s" state="o"/>
    <connection from="BC2B" to="B2BA" fromLane="1" toLane="1" via=":B_6_1" tl="B" linkIndex="7" dir="s" state="o"/>
    <connection from="BC2B" to="B2BA" fromLane="2" toLane="2" via=":B_6_2" tl="B" linkIndex="8" dir="s" state="o"/>
    <connection from="BC2B" to="B2TL" fromLane="2" toLane="3" via=":B_9_0" tl="B" linkIndex="9" dir="l" state="o"/>
    <connection from="C2TL" to="TL2E" fromLane="0" toLane="2" via=":TL_8_0" tl="TL" linkIndex="8" dir="s" state="o"/>
    <connection from="D2DA" to="DA2D" fromLane="0" toLane="0" via=":DA_0_0" tl="DA" linkIndex="0" dir="t" state="O"/>
    <connection from="D2DB" to="DB2D" fromLane="0" toLane="0" via=":DB_0_0" tl="DB" linkIndex="0" dir="t" state="O"/>
    <connection from="D2DC" to="DC2D" fromLane="0" toLane="0" via=":DC_0_0" tl="DC" linkIndex="0" dir="t" state="O"/>
    <connection from="D2TL" to="TL2B" fromLane="0" toLane="0" via=":TL_9_0" tl="TL" linkIndex="9" dir="s" state="o"/>
    <connection from="D2TL" to="TL2A" fromLane="0" toLane="0" via=":TL_10_0" tl="TL" linkIndex="10" dir="L" state="o"/>
    <connection from="DA2D" to="D2TL" fromLane="0" toLane="0" via=":D_2_0" tl="D" linkIndex="2" dir="r" state="o"/>
    <connection from="DA2D" to="D2DC" fromLane="0" toLane="0" via=":D_3_0" tl="D" linkIndex="3" dir="s" state="o"/>
    <connection from="DB2D" to="D2DA" fromLane="0" toLane="0" via=":D_4_0" tl="D" linkIndex="4" dir="r" state="O"/>
    <connection from="DB2D" to="D2TL" fromLane="0" toLane="0" via=":D_5_0" tl="D" linkIndex="5" dir="s" state="O"/>
    <connection from="DC2D" to="D2DB" fromLane="0" toLane="0" via=":D_6_0" tl="D" linkIndex="6" dir="r" state="o"/>
    <connection from="DC2D" to="D2DA" fromLane="0" toLane="0" via=":D_7_0" tl="D" linkIndex="7" dir="s" state="o"/>
    <connection from="E2EA" to="EA2E" fromLane="3" toLane="2" via=":EA_0_0" tl="EA" linkIndex="0" dir="t" state="O"/>
    <connection from="E2EB" to="EB2E" fromLane="3" toLane="2" via=":EB_0_0" tl="EB" linkIndex="0" dir="t" state="O"/>
    <connection from="E2EC" to="EC2E" fromLane="3" toLane="2" via=":EC_0_0" tl="EC" linkIndex="0" dir="t" state="O"/>
    <connection from="E2TL" to="TL2B" fromLane="0" toLane="0" via=":TL_11_0" tl="TL" linkIndex="11" dir="s" state="O"/>
    <connection from="E2TL" to="TL2B" fromLane="1" toLane="1" via=":TL_11_1" tl="TL" linkIndex="12" dir="s" state="O"/>
    <connection from="E2TL" to="TL2B" fromLane="2" toLane="2" via=":TL_11_2" tl="TL" linkIndex="13" dir="s" state="O"/>
    <connection from="E2TL" to="TL2A" fromLane="3" toLane="0" via=":TL_14_0" tl="TL" linkIndex="14" dir="l" state="o"/>
    <connection from="EA2E" to="E2TL" fromLane="0" toLane="0" via=":E_10_0" tl="E" linkIndex="10" dir="r" state="O"/>
    <connection from="EA2E" to="E2EC" fromLane="0" toLane="0" via=":E_11_0" tl="E" linkIndex="11" dir="s" state="O"/>
    <connection from="EA2E" to="E2EC" fromLane="1" toLane="1" via=":E_11_1" tl="E" linkIndex="12" dir="s" state="O"/>
    <connection from="EA2E" to="E2EC" fromLane="2" toLane="2" via=":E_11_2" tl="E" linkIndex="13" dir="s" state="O"/>
    <connection from="EA2E" to="E2EB" fromLane="2" toLane="3" via=":E_14_0" tl="E" linkIndex="14" dir="l" state="o"/>
    <connection from="EB2E" to="E2EA" fromLane="0" toLane="0" via=":E_15_0" tl="E" linkIndex="15" dir="r" state="o"/>
    <connection from="EB2E" to="E2TL" fromLane="0" toLane="0" via=":E_16_0" tl="E" linkIndex="16" dir="s" state="o"/>
    <connection from="EB2E" to="E2TL" fromLane="1" toLane="1" via=":E_16_1" tl="E" linkIndex="17" dir="s" state="o"/>
    <connection from="EB2E" to="E2TL" fromLane="2" toLane="2" via=":E_16_2" tl="E" linkIndex="18" dir="s" state="o"/>
    <connection from="EB2E" to="E2EC" fromLane="2" toLane="3" via=":E_19_0" tl="E" linkIndex="19" dir="l" state="o"/>
    <connection from="EC2E" to="E2EB" fromLane="0" toLane="0" via=":E_0_0" tl="E" linkIndex="0" dir="r" state="O"/>
    <connection from="EC2E" to="E2EA" fromLane="0" toLane="0" via=":E_1_0" tl="E" linkIndex="1" dir="s" state="O"/>
    <connection from="EC2E" to="E2EA" fromLane="1" toLane="1" via=":E_1_1" tl="E" linkIndex="2" dir="s" state="O"/>
    <connection from="EC2E" to="E2EA" fromLane="2" toLane="2" via=":E_1_2" tl="E" linkIndex="3" dir="s" state="O"/>
    <connection from="EC2E" to="E2TL" fromLane="2" toLane="3" via=":E_4_0" tl="E" linkIndex="4" dir="l" state="o"/>
    <connection from="TL2A" to="A2AC" fromLane="0" toLane="0" via=":A_4_0" tl="A" linkIndex="4" dir="r" state="O"/>
    <connection from="TL2A" to="A2AB" fromLane="0" toLane="0" via=":A_5_0" tl="A" linkIndex="5" dir="s" state="O"/>
    <connection from="TL2B" to="B2BC" fromLane="0" toLane="0" via=":B_10_0" tl="B" linkIndex="10" dir="r" state="O"/>
    <connection from="TL2B" to="B2BB" fromLane="0" toLane="0" via=":B_11_0" tl="B" linkIndex="11" dir="s" state="O"/>
    <connection from="TL2B" to="B2BB" fromLane="1" toLane="1" via=":B_11_1" tl="B" linkIndex="12" dir="s" state="O"/>
    <connection from="TL2B" to="B2BB" fromLane="2" toLane="2" via=":B_11_2" tl="B" linkIndex="13" dir="s" state="O"/>
    <connection from="TL2B" to="B2BA" fromLane="2" toLane="3" via=":B_14_0" tl="B" linkIndex="14" dir="l" state="o"/>
    <connection from="TL2D" to="D2DC" fromLane="0" toLane="0" via=":D_0_0" tl="D" linkIndex="0" dir="r" state="O"/>
    <connection from="TL2D" to="D2DB" fromLane="0" toLane="0" via=":D_1_0" tl="D" linkIndex="1" dir="s" state="O"/>
    <connection from="TL2E" to="E2EC" fromLane="0" toLane="0" via=":E_5_0" tl="E" linkIndex="5" dir="r" state="o"/>
    <connection from="TL2E" to="E2EB" fromLane="0" toLane="0" via=":E_6_0" tl="E" linkIndex="6" dir="s" state="o"/>
    <connection from="TL2E" to="E2EB" fromLane="1" toLane="1" via=":E_6_1" tl="E" linkIndex="7" dir="s" state="o"/>
    <connection from="TL2E" to="E2EB" fromLane="2" toLane="2" via=":E_6_2" tl="E" linkIndex="8" dir="s" state="o"/>
    <connection from="TL2E" to="E2EA" fromLane="2" toLane="3" via=":E_9_0" tl="E" linkIndex="9" dir="l" state="o"/>

    <connection from=":A_0" to="A2AA" fromLane="0" toLane="0" dir="r" state="M"/>
    <connection from=":A_1" to="A2TL" fromLane="0" toLane="0" dir="s" state="M"/>
    <connection from=":A_2" to="A2AB" fromLane="0" toLane="0" dir="r" state="M"/>
    <connection from=":A_3" to="A2AA" fromLane="0" toLane="0" dir="s" state="M"/>
    <connection from=":A_4" to="A2AC" fromLane="0" toLane="0" dir="r" state="M"/>
    <connection from=":A_5" to="A2AB" fromLane="0" toLane="0" dir="s" state="M"/>
    <connection from=":A_6" to="A2TL" fromLane="0" toLane="0" dir="r" state="M"/>
    <connection from=":A_7" to="A2AC" fromLane="0" toLane="0" dir="s" state="M"/>
    <connection from=":AA_0" to="AA2A" fromLane="0" toLane="0" dir="t" state="M"/>
    <connection from=":AB_0" to="AB2A" fromLane="0" toLane="0" dir="t" state="M"/>
    <connection from=":AC_0" to="AC2A" fromLane="0" toLane="0" dir="t" state="M"/>
    <connection from=":B_0" to="B2BA" fromLane="0" toLane="0" dir="r" state="M"/>
    <connection from=":B_1" to="B2TL" fromLane="0" toLane="0" dir="s" state="M"/>
    <connection from=":B_1" to="B2TL" fromLane="1" toLane="1" dir="s" state="M"/>
    <connection from=":B_1" to="B2TL" fromLane="2" toLane="2" dir="s" state="M"/>
    <connection from=":B_4" to="B2BC" fromLane="0" toLane="3" via=":B_20_0" dir="l" state="m"/>
    <connection from=":B_20" to="B2BC" fromLane="0" toLane="3" dir="l" state="M"/>
    <connection from=":B_5" to="B2BB" fromLane="0" toLane="0" dir="r" state="M"/>
    <connection from=":B_6" to="B2BA" fromLane="0" toLane="0" dir="s" state="M"/>
    <connection from=":B_6" to="B2BA" fromLane="1" toLane="1" dir="s" state="M"/>
    <connection from=":B_6" to="B2BA" fromLane="2" toLane="2" dir="s" state="M"/>
    <connection from=":B_9" to="B2TL" fromLane="0" toLane="3" via=":B_21_0" dir="l" state="m"/>
    <connection from=":B_21" to="B2TL" fromLane="0" toLane="3" dir="l" state="M"/>
    <connection from=":B_10" to="B2BC" fromLane="0" toLane="0" dir="r" state="M"/>
    <connection from=":B_11" to="B2BB" fromLane="0" toLane="0" dir="s" state="M"/>
    <connection from=":B_11" to="B2BB" fromLane="1" toLane="1" dir="s" state="M"/>
    <connection from=":B_11" to="B2BB" fromLane="2" toLane="2" dir="s" state="M"/>
    <connection from=":B_14" to="B2BA" fromLane="0" toLane="3" via=":B_22_0" dir="l" state="m"/>
    <connection from=":B_22" to="B2BA" fromLane="0" toLane="3" dir="l" state="M"/>
    <connection from=":B_15" to="B2TL" fromLane="0" toLane="0" dir="r" state="M"/>
    <connection from=":B_16" to="B2BC" fromLane="0" toLane="0" dir="s" state="M"/>
    <connection from=":B_16" to="B2BC" fromLane="1" toLane="1" dir="s" state="M"/>
    <connection from=":B_16" to="B2BC" fromLane="2" toLane="2" dir="s" state="M"/>
    <connection from=":B_19" to="B2BB" fromLane="0" toLane="3" via=":B_23_0" dir="l" state="m"/>
    <connection from=":B_23" to="B2BB" fromLane="0" toLane="3" dir="l" state="M"/>
    <connection from=":BA_0" to="BA2B" fromLane="0" toLane="2" dir="t" state="M"/>
    <connection from=":BB_0" to="BB2B" fromLane="0" toLane="2" dir="t" state="M"/>
    <connection from=":BC_0" to="BC2B" fromLane="0" toLane="2" dir="t" state="M"/>
    <connection from=":D_0" to="D2DC" fromLane="0" toLane="0" dir="r" state="M"/>
    <connection from=":D_1" to="D2DB" fromLane="0" toLane="0" dir="s" state="M"/>
    <connection from=":D_2" to="D2TL" fromLane="0" toLane="0" dir="r" state="M"/>
    <connection from=":D_3" to="D2DC" fromLane="0" toLane="0" dir="s" state="M"/>
    <connection from=":D_4" to="D2DA" fromLane="0" toLane="0" dir="r" state="M"/>
    <connection from=":D_5" to="D2TL" fromLane="0" toLane="0" dir="s" state="M"/>
    <connection from=":D_6" to="D2DB" fromLane="0" toLane="0" dir="r" state="M"/>
    <connection from=":D_7" to="D2DA" fromLane="0" toLane="0" dir="s" state="M"/>
    <connection from=":DA_0" to="DA2D" fromLane="0" toLane="0" dir="t" state="M"/>
    <connection from=":DB_0" to="DB2D" fromLane="0" toLane="0" dir="t" state="M"/>
    <connection from=":DC_0" to="DC2D" fromLane="0" toLane="0" dir="t" state="M"/>
    <connection from=":E_0" to="E2EB" fromLane="0" toLane="0" dir="r" state="M"/>
    <connection from=":E_1" to="E2EA" fromLane="0" toLane="0" dir="s" state="M"/>
    <connection from=":E_1" to="E2EA" fromLane="1" toLane="1" dir="s" state="M"/>
    <connection from=":E_1" to="E2EA" fromLane="2" toLane="2" dir="s" state="M"/>
    <connection from=":E_4" to="E2TL" fromLane="0" toLane="3" via=":E_20_0" dir="l" state="m"/>
    <connection from=":E_20" to="E2TL" fromLane="0" toLane="3" dir="l" state="M"/>
    <connection from=":E_5" to="E2EC" fromLane="0" toLane="0" dir="r" state="M"/>
    <connection from=":E_6" to="E2EB" fromLane="0" toLane="0" dir="s" state="M"/>
    <connection from=":E_6" to="E2EB" fromLane="1" toLane="1" dir="s" state="M"/>
    <connection from=":E_6" to="E2EB" fromLane="2" toLane="2" dir="s" state="M"/>
    <connection from=":E_9" to="E2EA" fromLane="0" toLane="3" via=":E_21_0" dir="l" state="m"/>
    <connection from=":E_21" to="E2EA" fromLane="0" toLane="3" dir="l" state="M"/>
    <connection from=":E_10" to="E2TL" fromLane="0" toLane="0" dir="r" state="M"/>
    <connection from=":E_11" to="E2EC" fromLane="0" toLane="0" dir="s" state="M"/>
    <connection from=":E_11" to="E2EC" fromLane="1" toLane="1" dir="s" state="M"/>
    <connection from=":E_11" to="E2EC" fromLane="2" toLane="2" dir="s" state="M"/>
    <connection from=":E_14" to="E2EB" fromLane="0" toLane="3" via=":E_22_0" dir="l" state="m"/>
    <connection from=":E_22" to="E2EB" fromLane="0" toLane="3" dir="l" state="M"/>
    <connection from=":E_15" to="E2EA" fromLane="0" toLane="0" dir="r" state="M"/>
    <connection from=":E_16" to="E2TL" fromLane="0" toLane="0" dir="s" state="M"/>
    <connection from=":E_16" to="E2TL" fromLane="1" toLane="1" dir="s" state="M"/>
    <connection from=":E_16" to="E2TL" fromLane="2" toLane="2" dir="s" state="M"/>
    <connection from=":E_19" to="E2EC" fromLane="0" toLane="3" via=":E_23_0" dir="l" state="m"/>
    <connection from=":E_23" to="E2EC" fromLane="0" toLane="3" dir="l" state="M"/>
    <connection from=":EA_0" to="EA2E" fromLane="0" toLane="2" dir="t" state="M"/>
    <connection from=":EB_0" to="EB2E" fromLane="0" toLane="2" dir="t" state="M"/>
    <connection from=":EC_0" to="EC2E" fromLane="0" toLane="2" dir="t" state="M"/>
    <connection from=":TL_0" to="TL2E" fromLane="0" toLane="0" dir="r" state="M"/>
    <connection from=":TL_1" to="TL2D" fromLane="0" toLane="0" dir="s" state="M"/>
    <connection from=":TL_2" to="TL2B" fromLane="0" toLane="2" via=":TL_15_0" dir="l" state="m"/>
    <connection from=":TL_15" to="TL2B" fromLane="0" toLane="2" dir="l" state="M"/>
    <connection from=":TL_3" to="TL2A" fromLane="0" toLane="0" dir="r" state="M"/>
    <connection from=":TL_4" to="TL2E" fromLane="0" toLane="0" dir="s" state="M"/>
    <connection from=":TL_4" to="TL2E" fromLane="1" toLane="1" dir="s" state="M"/>
    <connection from=":TL_4" to="TL2E" fromLane="2" toLane="2" dir="s" state="M"/>
    <connection from=":TL_4" to="TL2E" fromLane="3" toLane="2" dir="s" state="M"/>
    <connection from=":TL_8" to="TL2E" fromLane="0" toLane="2" dir="s" state="M"/>
    <connection from=":TL_9" to="TL2B" fromLane="0" toLane="0" dir="s" state="M"/>
    <connection from=":TL_10" to="TL2A" fromLane="0" toLane="0" dir="L" state="M"/>
    <connection from=":TL_11" to="TL2B" fromLane="0" toLane="0" dir="s" state="M"/>
    <connection from=":TL_11" to="TL2B" fromLane="1" toLane="1" dir="s" state="M"/>
    <connection from=":TL_11" to="TL2B" fromLane="2" toLane="2" dir="s" state="M"/>
    <connection from=":TL_14" to="TL2A" fromLane="0" toLane="0" via=":TL_16_0" dir="l" state="m"/>
    <connection from=":TL_16" to="TL2A" fromLane="0" toLane="0" dir="l" state="M"/>

</net>
